{"nodes": [{"group": 1, "id": "rKpXO"}, {"group": 1, "id": "EWZeo"}, {"group": 1, "id": "DmdgG"}, {"group": 1, "id": "g3ma"}, {"group": 1, "id": "PBvo6"}, {"group": 1, "id": "1jKzb"}, {"group": 1, "id": "n9l7"}, {"group": 1, "id": "7rRq"}, {"group": 0, "id": "wyvRk"}, {"group": 1, "id": "Q7XK"}, {"group": 1, "id": "4W0rO"}, {"group": 1, "id": "Gk2e"}, {"group": 1, "id": "QD89O"}, {"group": 1, "id": "gpqZd"}, {"group": 1, "id": "6Rnw"}, {"group": 1, "id": "m9Rn"}, {"group": 1, "id": "z20Pn"}, {"group": 1, "id": "o49Dp"}, {"group": 1, "id": "ypdWw"}, {"group": 1, "id": "wyPzK"}, {"group": 1, "id": "wyv9v"}, {"group": 1, "id": "Jypw"}, {"group": 1, "id": "55RNe"}, {"group": 1, "id": "z2mPK"}, {"group": 0, "id": "2Rb1p"}, {"group": 1, "id": "2RnZ7"}, {"group": 1, "id": "790o"}, {"group": 1, "id": "J6k5"}, {"group": 1, "id": "oy3PX"}, {"group": 1, "id": "AlqGP"}, {"group": 0, "id": "421e"}, {"group": 1, "id": "549zm"}, {"group": 1, "id": "jN723"}, {"group": 1, "id": "q7QV"}, {"group": 1, "id": "X9rGX"}, {"group": 1, "id": "GVZqw"}, {"group": 1, "id": "ypAyZ"}, {"group": 1, "id": "K3qlb"}, {"group": 1, "id": "pl06y"}, {"group": 0, "id": "3jPej"}, {"group": 1, "id": "GXAn"}, {"group": 1, "id": "J3am5"}, {"group": 1, "id": "6nRge"}, {"group": 1, "id": "grz5"}, {"group": 1, "id": "mj69D"}, {"group": 1, "id": "0jB49"}, {"group": 1, "id": "EweRP"}, {"group": 1, "id": "4rjOG"}, {"group": 1, "id": "ypvqZ"}, {"group": 1, "id": "JwXy"}, {"group": 1, "id": "eRmwy"}, {"group": 1, "id": "0jrn3"}, {"group": 1, "id": "7VENo"}, {"group": 1, "id": "Ew50X"}, {"group": 1, "id": "WEpoV"}, {"group": 1, "id": "RW87G"}, {"group": 1, "id": "NAz4J"}, {"group": 1, "id": "Dnvp"}, {"group": 1, "id": "BvE5W"}, {"group": 1, "id": "EqaG"}, {"group": 1, "id": "jNZal"}, {"group": 1, "id": "8r4gG"}, {"group": 1, "id": "Z9XD4"}, {"group": 1, "id": "B2Xz"}, {"group": 1, "id": "rKK3N"}, {"group": 1, "id": "yplQw"}, {"group": 1, "id": "QD3BE"}, {"group": 1, "id": "dB4dN"}, {"group": 1, "id": "3jJDk"}, {"group": 1, "id": "PBQNN"}, {"group": 1, "id": "qBbJ5"}, {"group": 1, "id": "RKrW"}, {"group": 1, "id": "Bqbp"}, {"group": 1, "id": "4W3JZ"}, {"group": 1, "id": "ayD7"}, {"group": 1, "id": "1jVBk"}, {"group": 1, "id": "oyweQ"}, {"group": 1, "id": "JA1A"}, {"group": 1, "id": "dmX5m"}, {"group": 1, "id": "gZBWl"}, {"group": 1, "id": "gpDzZ"}, {"group": 1, "id": "Jjkp"}, {"group": 1, "id": "NAzXk"}, {"group": 1, "id": "O4vdj"}, {"group": 0, "id": "DmlZw"}, {"group": 1, "id": "El8g"}, {"group": 1, "id": "O9ewB"}, {"group": 1, "id": "eRQKl"}, {"group": 1, "id": "Bvrw0"}, {"group": 1, "id": "Z05e"}, {"group": 1, "id": "3jzya"}, {"group": 1, "id": "WvB5"}, {"group": 1, "id": "pAvn"}, {"group": 1, "id": "r1Xr"}, {"group": 1, "id": "Wqol5"}, {"group": 1, "id": "A4y90"}, {"group": 1, "id": "06eD5"}, {"group": 1, "id": "vZ79R"}, {"group": 1, "id": "GVADo"}, {"group": 1, "id": "g2RW"}, {"group": 1, "id": "vZ2bO"}, {"group": 1, "id": "8zKEA"}, {"group": 1, "id": "eb1e"}, {"group": 1, "id": "pKXdl"}, {"group": 0, "id": "vpN4"}, {"group": 1, "id": "4Wnbq"}, {"group": 1, "id": "yypd9"}, {"group": 1, "id": "p0DN"}, {"group": 1, "id": "QpPR3"}, {"group": 1, "id": "gXZg"}, {"group": 0, "id": "06gP3"}, {"group": 1, "id": "Z9qEQ"}, {"group": 1, "id": "z9OGK"}, {"group": 1, "id": "O45Ey"}, {"group": 1, "id": "jNpWr"}, {"group": 1, "id": "08Oz"}, {"group": 1, "id": "OaR9"}, {"group": 1, "id": "RD0W"}, {"group": 1, "id": "6nG5w"}, {"group": 1, "id": "b9kOk"}, {"group": 1, "id": "AVDr"}, {"group": 1, "id": "8rnwm"}, {"group": 1, "id": "3pKV9"}, {"group": 1, "id": "vZlPb"}, {"group": 1, "id": "QyaO"}, {"group": 1, "id": "nKvXj"}, {"group": 1, "id": "GPpOo"}, {"group": 1, "id": "BvOmV"}, {"group": 0, "id": "GVyww"}, {"group": 1, "id": "qBj55"}, {"group": 1, "id": "GP6dK"}, {"group": 1, "id": "qJ15"}, {"group": 1, "id": "K3NRz"}, {"group": 1, "id": "dBK0w"}, {"group": 1, "id": "O4Bk9"}, {"group": 1, "id": "vZ42D"}, {"group": 1, "id": "vZWNb"}, {"group": 1, "id": "plmPn"}, {"group": 1, "id": "2RoaP"}, {"group": 1, "id": "zJrw"}, {"group": 1, "id": "GP7dK"}, {"group": 1, "id": "jNlNl"}, {"group": 1, "id": "jNmwG"}, {"group": 1, "id": "BA2bD"}, {"group": 1, "id": "GVa2K"}, {"group": 1, "id": "BvOP0"}, {"group": 1, "id": "7wk3"}, {"group": 1, "id": "WEyVQ"}, {"group": 1, "id": "QDZrO"}, {"group": 0, "id": "oyplN"}, {"group": 1, "id": "jNq8m"}, {"group": 1, "id": "gpvad"}, {"group": 1, "id": "9GRpZ"}, {"group": 1, "id": "QDBDD"}, {"group": 1, "id": "Dmnwa"}, {"group": 1, "id": "m3AJ"}, {"group": 1, "id": "b7P6"}, {"group": 0, "id": "NAEvq"}, {"group": 0, "id": "7prD3"}, {"group": 1, "id": "gZBVW"}, {"group": 1, "id": "lyZ61"}, {"group": 1, "id": "ZANE"}, {"group": 1, "id": "0jed9"}, {"group": 1, "id": "6nlRe"}, {"group": 1, "id": "06r96"}, {"group": 0, "id": "J3wOA"}, {"group": 1, "id": "Rvr1"}, {"group": 1, "id": "nOK6O"}, {"group": 1, "id": "27bv"}, {"group": 1, "id": "8rEvG"}, {"group": 1, "id": "O94g1"}, {"group": 0, "id": "ypvbJ"}, {"group": 1, "id": "plrgQ"}, {"group": 1, "id": "dBVl1"}, {"group": 1, "id": "QpRlR"}, {"group": 1, "id": "GPnnd"}, {"group": 1, "id": "gZmOd"}, {"group": 1, "id": "GyD3"}, {"group": 1, "id": "gZa1d"}, {"group": 1, "id": "kBwJE"}, {"group": 1, "id": "gpZog"}, {"group": 1, "id": "3jW1J"}, {"group": 1, "id": "pKaBX"}, {"group": 1, "id": "q0gXm"}, {"group": 1, "id": "2B87"}, {"group": 1, "id": "QDbvn"}, {"group": 1, "id": "JegB"}, {"group": 1, "id": "DmWzd"}, {"group": 1, "id": "1KOE"}, {"group": 1, "id": "D9ep"}, {"group": 1, "id": "GVOGK"}, {"group": 1, "id": "84P2"}, {"group": 1, "id": "O4Pw2"}, {"group": 1, "id": "9Gd50"}, {"group": 1, "id": "54aBr"}, {"group": 1, "id": "ErQa"}, {"group": 1, "id": "va8O"}, {"group": 1, "id": "jZBDN"}, {"group": 0, "id": "QpR5O"}, {"group": 1, "id": "dBvVK"}, {"group": 1, "id": "Ew8zB"}, {"group": 1, "id": "vEZd"}, {"group": 1, "id": "w5eK"}, {"group": 1, "id": "XJ74A"}, {"group": 1, "id": "z2vKy"}, {"group": 1, "id": "q07yR"}, {"group": 1, "id": "AlNg0"}, {"group": 1, "id": "dBAdN"}, {"group": 1, "id": "Ewo0o"}, {"group": 1, "id": "GVO86"}, {"group": 1, "id": "J3lAK"}, {"group": 1, "id": "4lJZ"}, {"group": 1, "id": "yzGJ"}, {"group": 1, "id": "KmbwJ"}, {"group": 0, "id": "gZXnW"}, {"group": 1, "id": "J3j4y"}, {"group": 1, "id": "dKrv"}, {"group": 1, "id": "jN9Nr"}, {"group": 1, "id": "QDJ4D"}, {"group": 1, "id": "vWD9"}, {"group": 1, "id": "w8kA"}, {"group": 1, "id": "WEQVX"}, {"group": 1, "id": "ND5J"}, {"group": 1, "id": "Q2Ko"}, {"group": 1, "id": "BvEBp"}, {"group": 1, "id": "X9P2p"}, {"group": 0, "id": "ypv3P"}, {"group": 1, "id": "9gKD"}, {"group": 0, "id": "z2v34"}, {"group": 1, "id": "z95p6"}, {"group": 1, "id": "mj3DZ"}, {"group": 1, "id": "VrRb"}, {"group": 0, "id": "GV7a6"}, {"group": 1, "id": "06Zod"}, {"group": 1, "id": "Qpmen"}, {"group": 1, "id": "8zkdm"}, {"group": 1, "id": "7Vj8b"}, {"group": 1, "id": "6Wge"}, {"group": 0, "id": "m75E0"}, {"group": 1, "id": "aVAR"}, {"group": 1, "id": "eWRy"}, {"group": 1, "id": "a7yDp"}, {"group": 1, "id": "kB69R"}, {"group": 0, "id": "O4elj"}, {"group": 1, "id": "NAnpm"}, {"group": 0, "id": "Vjlz6"}, {"group": 1, "id": "Alr5l"}, {"group": 1, "id": "r92Q"}, {"group": 1, "id": "D2yP"}, {"group": 0, "id": "4npG"}, {"group": 1, "id": "A47a5"}, {"group": 1, "id": "DmGz0"}, {"group": 1, "id": "zzan"}, {"group": 0, "id": "XD1y"}, {"group": 1, "id": "dBgvw"}, {"group": 1, "id": "vZBB9"}, {"group": 1, "id": "a7ld3"}, {"group": 1, "id": "lBzp"}, {"group": 1, "id": "JmyJ5"}, {"group": 1, "id": "rKv0m"}, {"group": 1, "id": "RADPG"}, {"group": 1, "id": "aaXA"}, {"group": 1, "id": "O4Peb"}, {"group": 1, "id": "NApZ0"}, {"group": 1, "id": "54aA5"}, {"group": 1, "id": "jZ80X"}, {"group": 1, "id": "3j34a"}, {"group": 1, "id": "QDVbK"}, {"group": 1, "id": "yoyZ"}, {"group": 1, "id": "qnJ7"}, {"group": 1, "id": "BAb5W"}, {"group": 1, "id": "QpzWK"}, {"group": 1, "id": "wzrl"}, {"group": 1, "id": "7yBk"}, {"group": 1, "id": "ewel"}, {"group": 1, "id": "lypB1"}, {"group": 1, "id": "RAV8Z"}, {"group": 1, "id": "q0Egm"}, {"group": 1, "id": "RW2Xr"}, {"group": 1, "id": "eRNNb"}, {"group": 0, "id": "Nw6m"}, {"group": 0, "id": "eREry"}, {"group": 1, "id": "q01l2"}, {"group": 1, "id": "pB11"}, {"group": 1, "id": "pKXan"}, {"group": 1, "id": "qBqo9"}, {"group": 1, "id": "8zVOA"}, {"group": 1, "id": "GV7pK"}, {"group": 0, "id": "G5Jo"}, {"group": 0, "id": "QDGnK"}, {"group": 1, "id": "NA2Na"}, {"group": 1, "id": "Nb3q0"}, {"group": 1, "id": "1Oeq"}, {"group": 1, "id": "GqKJ"}, {"group": 1, "id": "v2jOz"}, {"group": 1, "id": "o4Qee"}, {"group": 0, "id": "mXkb"}, {"group": 1, "id": "Algmq"}, {"group": 1, "id": "XJKzK"}, {"group": 1, "id": "Dm20P"}, {"group": 1, "id": "Z3gAv"}, {"group": 1, "id": "Vj3gv"}, {"group": 1, "id": "wy5AK"}, {"group": 1, "id": "K602"}, {"group": 1, "id": "1r0Z"}, {"group": 1, "id": "7p5NB"}, {"group": 1, "id": "QXX3"}, {"group": 1, "id": "pXEy"}, {"group": 1, "id": "8rBVm"}, {"group": 1, "id": "O98ez"}, {"group": 1, "id": "m8eb"}, {"group": 1, "id": "06W9Z"}, {"group": 1, "id": "3ppvb"}, {"group": 1, "id": "8r3By"}, {"group": 1, "id": "pRX1"}, {"group": 1, "id": "rKdr7"}, {"group": 1, "id": "ebZ9"}, {"group": 1, "id": "XJGOp"}, {"group": 1, "id": "RzA1"}, {"group": 1, "id": "Gbpd"}, {"group": 1, "id": "KrrD"}, {"group": 1, "id": "JVQy"}, {"group": 1, "id": "8rGk2"}, {"group": 1, "id": "O9GE1"}, {"group": 1, "id": "qBrBv"}, {"group": 1, "id": "lNd3m"}, {"group": 1, "id": "BA935"}, {"group": 1, "id": "erGw"}, {"group": 1, "id": "JZbA"}, {"group": 1, "id": "X9aDe"}, {"group": 1, "id": "jNNb4"}, {"group": 1, "id": "b9NZw"}, {"group": 1, "id": "AlgDJ"}, {"group": 1, "id": "z2OGw"}, {"group": 1, "id": "Nn8k"}, {"group": 1, "id": "qBOv7"}, {"group": 1, "id": "4W2W9"}, {"group": 1, "id": "Z9n1B"}, {"group": 1, "id": "PB0p9"}, {"group": 1, "id": "kg0E"}, {"group": 1, "id": "zQ2e"}, {"group": 1, "id": "GV7ow"}, {"group": 0, "id": "Nbja0"}, {"group": 1, "id": "kD6Nv"}, {"group": 1, "id": "mj3X3"}, {"group": 0, "id": "4Z9e"}, {"group": 1, "id": "Qbro"}, {"group": 1, "id": "wyRlO"}, {"group": 1, "id": "GVOZn"}, {"group": 1, "id": "aJVv"}, {"group": 1, "id": "o4J4z"}, {"group": 1, "id": "6rdD"}], "links": [{"source": "rKpXO", "target": "84P2", "value": 1}, {"source": "EWZeo", "target": "plrgQ", "value": 1}, {"source": "DmdgG", "target": "NAnpm", "value": 0}, {"source": "g3ma", "target": "K3NRz", "value": 0}, {"source": "g3ma", "target": "OaR9", "value": 0}, {"source": "PBvo6", "target": "pAvn", "value": 0}, {"source": "PBvo6", "target": "wzrl", "value": 0}, {"source": "1jKzb", "target": "Z05e", "value": 0}, {"source": "1jKzb", "target": "NAnpm", "value": 0}, {"source": "n9l7", "target": "AlgDJ", "value": 0}, {"source": "n9l7", "target": "oy3PX", "value": 0}, {"source": "n9l7", "target": "vZlPb", "value": 0}, {"source": "n9l7", "target": "BvEBp", "value": 0}, {"source": "n9l7", "target": "wyv9v", "value": 0}, {"source": "7rRq", "target": "K3NRz", "value": 0}, {"source": "7rRq", "target": "q07yR", "value": 0}, {"source": "wyvRk", "target": "O4elj", "value": 0}, {"source": "Q7XK", "target": "pB11", "value": 1}, {"source": "Q7XK", "target": "jN9Nr", "value": 0}, {"source": "Q7XK", "target": "EweRP", "value": 0}, {"source": "Q7XK", "target": "plrgQ", "value": 0}, {"source": "Q7XK", "target": "vZlPb", "value": 0}, {"source": "4W0rO", "target": "gZmOd", "value": 0}, {"source": "Gk2e", "target": "pB11", "value": 1}, {"source": "Gk2e", "target": "3ppvb", "value": 0}, {"source": "Gk2e", "target": "z9OGK", "value": 1}, {"source": "Gk2e", "target": "Bvrw0", "value": 0}, {"source": "Gk2e", "target": "oy3PX", "value": 1}, {"source": "Gk2e", "target": "pAvn", "value": 0}, {"source": "Gk2e", "target": "vZlPb", "value": 0}, {"source": "Gk2e", "target": "Dmnwa", "value": 0}, {"source": "Gk2e", "target": "ebZ9", "value": 0}, {"source": "Gk2e", "target": "OaR9", "value": 2}, {"source": "QD89O", "target": "Ew8zB", "value": 0}, {"source": "QD89O", "target": "BAb5W", "value": 0}, {"source": "gpqZd", "target": "m8eb", "value": 0}, {"source": "6Rnw", "target": "QpRlR", "value": 0}, {"source": "6Rnw", "target": "NA2Na", "value": 2}, {"source": "6Rnw", "target": "BvOmV", "value": 0}, {"source": "6Rnw", "target": "gZBWl", "value": 0}, {"source": "6Rnw", "target": "Qbro", "value": 2}, {"source": "6Rnw", "target": "27bv", "value": 0}, {"source": "6Rnw", "target": "Z05e", "value": 0}, {"source": "6Rnw", "target": "w8kA", "value": 0}, {"source": "6Rnw", "target": "JmyJ5", "value": 0}, {"source": "6Rnw", "target": "K3NRz", "value": 1}, {"source": "6Rnw", "target": "jNZal", "value": 2}, {"source": "6Rnw", "target": "WvB5", "value": 0}, {"source": "6Rnw", "target": "Ew8zB", "value": 0}, {"source": "6Rnw", "target": "84P2", "value": 0}, {"source": "6Rnw", "target": "GPpOo", "value": 0}, {"source": "6Rnw", "target": "OaR9", "value": 1}, {"source": "m9Rn", "target": "ZANE", "value": 0}, {"source": "m9Rn", "target": "QDJ4D", "value": 0}, {"source": "m9Rn", "target": "vZlPb", "value": 0}, {"source": "z20Pn", "target": "grz5", "value": 0}, {"source": "o49Dp", "target": "JmyJ5", "value": 0}, {"source": "ypdWw", "target": "kD6Nv", "value": 0}, {"source": "wyPzK", "target": "X9P2p", "value": 0}, {"source": "wyPzK", "target": "ewel", "value": 0}, {"source": "Jypw", "target": "pAvn", "value": 0}, {"source": "55RNe", "target": "7VENo", "value": 1}, {"source": "55RNe", "target": "BAb5W", "value": 0}, {"source": "55RNe", "target": "QXX3", "value": 0}, {"source": "55RNe", "target": "QpPR3", "value": 0}, {"source": "z2mPK", "target": "BA2bD", "value": 0}, {"source": "z2mPK", "target": "gZBWl", "value": 0}, {"source": "z2mPK", "target": "jN9Nr", "value": 0}, {"source": "z2mPK", "target": "m8eb", "value": 0}, {"source": "z2mPK", "target": "27bv", "value": 0}, {"source": "z2mPK", "target": "vZlPb", "value": 0}, {"source": "z2mPK", "target": "QpPR3", "value": 0}, {"source": "z2mPK", "target": "vZWNb", "value": 0}, {"source": "2RnZ7", "target": "WvB5", "value": 1}, {"source": "2RnZ7", "target": "06Zod", "value": 0}, {"source": "2RnZ7", "target": "J3j4y", "value": 0}, {"source": "2RnZ7", "target": "Alr5l", "value": 0}, {"source": "2RnZ7", "target": "vZBB9", "value": 1}, {"source": "2RnZ7", "target": "oy3PX", "value": 0}, {"source": "2RnZ7", "target": "aVAR", "value": 1}, {"source": "2RnZ7", "target": "pAvn", "value": 0}, {"source": "2RnZ7", "target": "K3NRz", "value": 5}, {"source": "2RnZ7", "target": "EqaG", "value": 0}, {"source": "2RnZ7", "target": "vZlPb", "value": 0}, {"source": "2RnZ7", "target": "jNZal", "value": 1}, {"source": "2RnZ7", "target": "Ew8zB", "value": 1}, {"source": "2RnZ7", "target": "vZ79R", "value": 0}, {"source": "2RnZ7", "target": "OaR9", "value": 2}, {"source": "790o", "target": "K3NRz", "value": 0}, {"source": "790o", "target": "DmWzd", "value": 0}, {"source": "790o", "target": "m8eb", "value": 0}, {"source": "J6k5", "target": "kD6Nv", "value": 0}, {"source": "J6k5", "target": "K3NRz", "value": 1}, {"source": "J6k5", "target": "jNZal", "value": 0}, {"source": "J6k5", "target": "Nb3q0", "value": 0}, {"source": "J6k5", "target": "27bv", "value": 1}, {"source": "oy3PX", "target": "QpRlR", "value": 0}, {"source": "oy3PX", "target": "BAb5W", "value": 0}, {"source": "oy3PX", "target": "7VENo", "value": 1}, {"source": "oy3PX", "target": "Gk2e", "value": 0}, {"source": "oy3PX", "target": "Alr5l", "value": 0}, {"source": "oy3PX", "target": "vZBB9", "value": 0}, {"source": "oy3PX", "target": "QDJ4D", "value": 0}, {"source": "oy3PX", "target": "m8eb", "value": 1}, {"source": "oy3PX", "target": "X9rGX", "value": 0}, {"source": "oy3PX", "target": "ZANE", "value": 0}, {"source": "oy3PX", "target": "vZ42D", "value": 0}, {"source": "oy3PX", "target": "vZlPb", "value": 0}, {"source": "oy3PX", "target": "GyD3", "value": 0}, {"source": "oy3PX", "target": "dmX5m", "value": 0}, {"source": "oy3PX", "target": "pAvn", "value": 0}, {"source": "AlqGP", "target": "K3NRz", "value": 0}, {"source": "421e", "target": "Nbja0", "value": 0}, {"source": "jN723", "target": "gZmOd", "value": 0}, {"source": "q7QV", "target": "BAb5W", "value": 0}, {"source": "q7QV", "target": "Q7XK", "value": 0}, {"source": "q7QV", "target": "pKXan", "value": 0}, {"source": "X9rGX", "target": "plrgQ", "value": 2}, {"source": "X9rGX", "target": "JmyJ5", "value": 2}, {"source": "ypAyZ", "target": "K3NRz", "value": 1}, {"source": "ypAyZ", "target": "grz5", "value": 0}, {"source": "K3qlb", "target": "jN9Nr", "value": 0}, {"source": "K3qlb", "target": "vZlPb", "value": 0}, {"source": "K3qlb", "target": "BvOmV", "value": 0}, {"source": "pl06y", "target": "K3NRz", "value": 0}, {"source": "3jPej", "target": "m75E0", "value": 0}, {"source": "J3am5", "target": "vZBB9", "value": 0}, {"source": "J3am5", "target": "gpZog", "value": 1}, {"source": "6nRge", "target": "K3NRz", "value": 0}, {"source": "6nRge", "target": "vZlPb", "value": 0}, {"source": "6nRge", "target": "O94g1", "value": 0}, {"source": "mj69D", "target": "O94g1", "value": 0}, {"source": "0jB49", "target": "K3NRz", "value": 0}, {"source": "EweRP", "target": "K3NRz", "value": 0}, {"source": "EweRP", "target": "BvEBp", "value": 0}, {"source": "EweRP", "target": "vZlPb", "value": 0}, {"source": "EweRP", "target": "7VENo", "value": 0}, {"source": "EweRP", "target": "pAvn", "value": 0}, {"source": "4rjOG", "target": "grz5", "value": 0}, {"source": "ypvqZ", "target": "vZlPb", "value": 0}, {"source": "ypvqZ", "target": "grz5", "value": 0}, {"source": "JwXy", "target": "grz5", "value": 0}, {"source": "eRmwy", "target": "plrgQ", "value": 0}, {"source": "0jrn3", "target": "erGw", "value": 0}, {"source": "0jrn3", "target": "7VENo", "value": 0}, {"source": "0jrn3", "target": "Nb3q0", "value": 0}, {"source": "0jrn3", "target": "2RnZ7", "value": 0}, {"source": "0jrn3", "target": "1r0Z", "value": 0}, {"source": "0jrn3", "target": "ZANE", "value": 0}, {"source": "0jrn3", "target": "jNZal", "value": 0}, {"source": "0jrn3", "target": "gZa1d", "value": 0}, {"source": "0jrn3", "target": "mj3X3", "value": 0}, {"source": "0jrn3", "target": "kB69R", "value": 0}, {"source": "0jrn3", "target": "q0gXm", "value": 0}, {"source": "7VENo", "target": "Ewo0o", "value": 1}, {"source": "7VENo", "target": "O94g1", "value": 0}, {"source": "7VENo", "target": "oy3PX", "value": 2}, {"source": "7VENo", "target": "aVAR", "value": 0}, {"source": "7VENo", "target": "wzrl", "value": 0}, {"source": "7VENo", "target": "dB4dN", "value": 0}, {"source": "7VENo", "target": "0jrn3", "value": 0}, {"source": "7VENo", "target": "3jJDk", "value": 1}, {"source": "7VENo", "target": "qBbJ5", "value": 0}, {"source": "7VENo", "target": "dBvVK", "value": 0}, {"source": "7VENo", "target": "OaR9", "value": 5}, {"source": "7VENo", "target": "dBgvw", "value": 0}, {"source": "7VENo", "target": "BAb5W", "value": 2}, {"source": "7VENo", "target": "Nb3q0", "value": 2}, {"source": "7VENo", "target": "6nG5w", "value": 0}, {"source": "7VENo", "target": "27bv", "value": 0}, {"source": "7VENo", "target": "ZANE", "value": 2}, {"source": "7VENo", "target": "gZmOd", "value": 1}, {"source": "7VENo", "target": "ayD7", "value": 1}, {"source": "7VENo", "target": "w8kA", "value": 0}, {"source": "7VENo", "target": "vZlPb", "value": 2}, {"source": "7VENo", "target": "DmGz0", "value": 0}, {"source": "7VENo", "target": "6nlRe", "value": 1}, {"source": "7VENo", "target": "Z3gAv", "value": 0}, {"source": "7VENo", "target": "BvEBp", "value": 0}, {"source": "7VENo", "target": "gZBWl", "value": 0}, {"source": "7VENo", "target": "vZBB9", "value": 2}, {"source": "7VENo", "target": "Z05e", "value": 0}, {"source": "7VENo", "target": "qBj55", "value": 0}, {"source": "7VENo", "target": "zQ2e", "value": 0}, {"source": "7VENo", "target": "JmyJ5", "value": 2}, {"source": "7VENo", "target": "EqaG", "value": 0}, {"source": "7VENo", "target": "54aA5", "value": 0}, {"source": "7VENo", "target": "jNZal", "value": 0}, {"source": "7VENo", "target": "gpDzZ", "value": 0}, {"source": "7VENo", "target": "va8O", "value": 1}, {"source": "7VENo", "target": "Ew8zB", "value": 0}, {"source": "7VENo", "target": "kD6Nv", "value": 2}, {"source": "7VENo", "target": "aaXA", "value": 0}, {"source": "7VENo", "target": "7wk3", "value": 0}, {"source": "7VENo", "target": "06Zod", "value": 0}, {"source": "7VENo", "target": "wy5AK", "value": 0}, {"source": "7VENo", "target": "pKaBX", "value": 0}, {"source": "7VENo", "target": "Alr5l", "value": 0}, {"source": "7VENo", "target": "Q2Ko", "value": 0}, {"source": "7VENo", "target": "7p5NB", "value": 0}, {"source": "7VENo", "target": "jNq8m", "value": 1}, {"source": "7VENo", "target": "6rdD", "value": 0}, {"source": "7VENo", "target": "55RNe", "value": 0}, {"source": "7VENo", "target": "NAzXk", "value": 1}, {"source": "Ew50X", "target": "grz5", "value": 0}, {"source": "WEpoV", "target": "w8kA", "value": 0}, {"source": "WEpoV", "target": "BAb5W", "value": 0}, {"source": "WEpoV", "target": "7VENo", "value": 0}, {"source": "WEpoV", "target": "Ew8zB", "value": 0}, {"source": "RW87G", "target": "grz5", "value": 0}, {"source": "Dnvp", "target": "vZ79R", "value": 0}, {"source": "BvE5W", "target": "ebZ9", "value": 0}, {"source": "EqaG", "target": "jN9Nr", "value": 0}, {"source": "EqaG", "target": "K3NRz", "value": 0}, {"source": "EqaG", "target": "7VENo", "value": 0}, {"source": "EqaG", "target": "549zm", "value": 0}, {"source": "jNZal", "target": "7Vj8b", "value": 0}, {"source": "jNZal", "target": "Ewo0o", "value": 0}, {"source": "jNZal", "target": "Bvrw0", "value": 0}, {"source": "jNZal", "target": "Z05e", "value": 2}, {"source": "jNZal", "target": "DmWzd", "value": 0}, {"source": "jNZal", "target": "Dmnwa", "value": 1}, {"source": "jNZal", "target": "BA2bD", "value": 0}, {"source": "jNZal", "target": "D9ep", "value": 1}, {"source": "jNZal", "target": "OaR9", "value": 4}, {"source": "jNZal", "target": "WvB5", "value": 0}, {"source": "jNZal", "target": "AlgDJ", "value": 0}, {"source": "jNZal", "target": "7VENo", "value": 1}, {"source": "jNZal", "target": "Nb3q0", "value": 2}, {"source": "jNZal", "target": "zJrw", "value": 0}, {"source": "jNZal", "target": "QDJ4D", "value": 0}, {"source": "jNZal", "target": "4W3JZ", "value": 0}, {"source": "jNZal", "target": "w8kA", "value": 0}, {"source": "jNZal", "target": "vZlPb", "value": 2}, {"source": "jNZal", "target": "84P2", "value": 1}, {"source": "jNZal", "target": "aaXA", "value": 0}, {"source": "jNZal", "target": "GPpOo", "value": 0}, {"source": "jNZal", "target": "BvOmV", "value": 1}, {"source": "jNZal", "target": "ypAyZ", "value": 0}, {"source": "jNZal", "target": "gZBWl", "value": 2}, {"source": "jNZal", "target": "vZBB9", "value": 2}, {"source": "jNZal", "target": "6Rnw", "value": 0}, {"source": "jNZal", "target": "K3NRz", "value": 4}, {"source": "jNZal", "target": "O4vdj", "value": 0}, {"source": "jNZal", "target": "va8O", "value": 1}, {"source": "jNZal", "target": "4Wnbq", "value": 1}, {"source": "jNZal", "target": "kD6Nv", "value": 0}, {"source": "jNZal", "target": "Gbpd", "value": 0}, {"source": "jNZal", "target": "27bv", "value": 1}, {"source": "jNZal", "target": "Q2Ko", "value": 0}, {"source": "jNZal", "target": "aJVv", "value": 0}, {"source": "jNZal", "target": "6rdD", "value": 0}, {"source": "jNZal", "target": "2RnZ7", "value": 0}, {"source": "8r4gG", "target": "grz5", "value": 0}, {"source": "B2Xz", "target": "K3NRz", "value": 1}, {"source": "rKK3N", "target": "NAzXk", "value": 0}, {"source": "yplQw", "target": "w8kA", "value": 0}, {"source": "yplQw", "target": "g2RW", "value": 1}, {"source": "QD3BE", "target": "plrgQ", "value": 0}, {"source": "QD3BE", "target": "7VENo", "value": 0}, {"source": "QD3BE", "target": "OaR9", "value": 0}, {"source": "dB4dN", "target": "7VENo", "value": 0}, {"source": "dB4dN", "target": "JmyJ5", "value": 0}, {"source": "dB4dN", "target": "J3j4y", "value": 0}, {"source": "3jJDk", "target": "XJKzK", "value": 0}, {"source": "3jJDk", "target": "27bv", "value": 0}, {"source": "PBQNN", "target": "EqaG", "value": 0}, {"source": "RKrW", "target": "vZlPb", "value": 0}, {"source": "Bqbp", "target": "WvB5", "value": 0}, {"source": "Bqbp", "target": "27bv", "value": 0}, {"source": "Bqbp", "target": "BvOmV", "value": 0}, {"source": "Bqbp", "target": "BA2bD", "value": 0}, {"source": "Bqbp", "target": "J3j4y", "value": 0}, {"source": "4W3JZ", "target": "vZBB9", "value": 0}, {"source": "4W3JZ", "target": "kD6Nv", "value": 1}, {"source": "4W3JZ", "target": "jNZal", "value": 0}, {"source": "4W3JZ", "target": "Ewo0o", "value": 0}, {"source": "4W3JZ", "target": "NAzXk", "value": 0}, {"source": "ayD7", "target": "7VENo", "value": 1}, {"source": "oyweQ", "target": "kD6Nv", "value": 0}, {"source": "oyweQ", "target": "K3NRz", "value": 0}, {"source": "oyweQ", "target": "jNpWr", "value": 0}, {"source": "oyweQ", "target": "Q2Ko", "value": 0}, {"source": "oyweQ", "target": "7VENo", "value": 0}, {"source": "JA1A", "target": "Z05e", "value": 0}, {"source": "JA1A", "target": "Wqol5", "value": 0}, {"source": "JA1A", "target": "EqaG", "value": 0}, {"source": "JA1A", "target": "jNZal", "value": 1}, {"source": "JA1A", "target": "oyweQ", "value": 0}, {"source": "JA1A", "target": "84P2", "value": 0}, {"source": "gZBWl", "target": "BAb5W", "value": 0}, {"source": "gZBWl", "target": "b7P6", "value": 0}, {"source": "gZBWl", "target": "Nb3q0", "value": 0}, {"source": "gZBWl", "target": "K3NRz", "value": 0}, {"source": "gZBWl", "target": "pAvn", "value": 0}, {"source": "gZBWl", "target": "6Rnw", "value": 0}, {"source": "gZBWl", "target": "QDJ4D", "value": 0}, {"source": "gZBWl", "target": "27bv", "value": 0}, {"source": "gZBWl", "target": "Qpmen", "value": 0}, {"source": "gZBWl", "target": "w8kA", "value": 0}, {"source": "gZBWl", "target": "vZlPb", "value": 1}, {"source": "gZBWl", "target": "jNZal", "value": 2}, {"source": "gZBWl", "target": "4W2W9", "value": 0}, {"source": "gZBWl", "target": "va8O", "value": 1}, {"source": "gZBWl", "target": "3jJDk", "value": 0}, {"source": "gZBWl", "target": "84P2", "value": 0}, {"source": "gZBWl", "target": "b9NZw", "value": 0}, {"source": "gZBWl", "target": "OaR9", "value": 2}, {"source": "gpDzZ", "target": "K3NRz", "value": 1}, {"source": "gpDzZ", "target": "Ewo0o", "value": 1}, {"source": "gpDzZ", "target": "JmyJ5", "value": 1}, {"source": "gpDzZ", "target": "6Rnw", "value": 0}, {"source": "Jjkp", "target": "84P2", "value": 0}, {"source": "Jjkp", "target": "kD6Nv", "value": 2}, {"source": "DmlZw", "target": "7prD3", "value": 0}, {"source": "El8g", "target": "K3NRz", "value": 2}, {"source": "El8g", "target": "kD6Nv", "value": 0}, {"source": "El8g", "target": "XJKzK", "value": 0}, {"source": "O9ewB", "target": "gZa1d", "value": 0}, {"source": "eRQKl", "target": "Ewo0o", "value": 0}, {"source": "Z05e", "target": "plrgQ", "value": 2}, {"source": "Z05e", "target": "Dmnwa", "value": 1}, {"source": "Z05e", "target": "vZBB9", "value": 1}, {"source": "Z05e", "target": "NAnpm", "value": 1}, {"source": "Z05e", "target": "WvB5", "value": 0}, {"source": "Z05e", "target": "BAb5W", "value": 0}, {"source": "Z05e", "target": "7VENo", "value": 1}, {"source": "Z05e", "target": "Wqol5", "value": 2}, {"source": "Z05e", "target": "w8kA", "value": 0}, {"source": "Z05e", "target": "84P2", "value": 1}, {"source": "Z05e", "target": "NAz4J", "value": 0}, {"source": "Z05e", "target": "X9P2p", "value": 0}, {"source": "Z05e", "target": "AVDr", "value": 2}, {"source": "Z05e", "target": "eRNNb", "value": 0}, {"source": "Z05e", "target": "6Rnw", "value": 0}, {"source": "Z05e", "target": "9gKD", "value": 0}, {"source": "Z05e", "target": "JmyJ5", "value": 1}, {"source": "Z05e", "target": "jNZal", "value": 3}, {"source": "Z05e", "target": "va8O", "value": 0}, {"source": "Z05e", "target": "aaXA", "value": 0}, {"source": "Z05e", "target": "pKaBX", "value": 1}, {"source": "Z05e", "target": "NApZ0", "value": 1}, {"source": "Z05e", "target": "aJVv", "value": 0}, {"source": "3jzya", "target": "vZBB9", "value": 0}, {"source": "3jzya", "target": "jNq8m", "value": 0}, {"source": "3jzya", "target": "D9ep", "value": 0}, {"source": "3jzya", "target": "plrgQ", "value": 2}, {"source": "3jzya", "target": "JmyJ5", "value": 0}, {"source": "WvB5", "target": "QpRlR", "value": 0}, {"source": "WvB5", "target": "b7P6", "value": 0}, {"source": "WvB5", "target": "X9P2p", "value": 0}, {"source": "WvB5", "target": "J3j4y", "value": 0}, {"source": "WvB5", "target": "2RnZ7", "value": 0}, {"source": "WvB5", "target": "27bv", "value": 1}, {"source": "WvB5", "target": "6Rnw", "value": 0}, {"source": "WvB5", "target": "54aBr", "value": 0}, {"source": "WvB5", "target": "Z05e", "value": 0}, {"source": "WvB5", "target": "K3NRz", "value": 1}, {"source": "WvB5", "target": "rKdr7", "value": 2}, {"source": "WvB5", "target": "jNZal", "value": 0}, {"source": "WvB5", "target": "Nb3q0", "value": 0}, {"source": "WvB5", "target": "va8O", "value": 0}, {"source": "WvB5", "target": "84P2", "value": 0}, {"source": "WvB5", "target": "OaR9", "value": 0}, {"source": "WvB5", "target": "kD6Nv", "value": 1}, {"source": "WvB5", "target": "06W9Z", "value": 0}, {"source": "WvB5", "target": "wzrl", "value": 0}, {"source": "pAvn", "target": "84P2", "value": 1}, {"source": "r1Xr", "target": "Algmq", "value": 0}, {"source": "r1Xr", "target": "NAnpm", "value": 0}, {"source": "Wqol5", "target": "7Vj8b", "value": 1}, {"source": "Wqol5", "target": "plrgQ", "value": 1}, {"source": "Wqol5", "target": "Z05e", "value": 1}, {"source": "Wqol5", "target": "jNZal", "value": 0}, {"source": "Wqol5", "target": "06r96", "value": 0}, {"source": "Wqol5", "target": "D9ep", "value": 0}, {"source": "Wqol5", "target": "NAnpm", "value": 1}, {"source": "A4y90", "target": "oy3PX", "value": 1}, {"source": "06eD5", "target": "Z3gAv", "value": 0}, {"source": "06eD5", "target": "kg0E", "value": 0}, {"source": "vZ79R", "target": "BAb5W", "value": 0}, {"source": "vZ79R", "target": "wzrl", "value": 0}, {"source": "GVADo", "target": "K3NRz", "value": 0}, {"source": "GVADo", "target": "JmyJ5", "value": 0}, {"source": "vZ2bO", "target": "NAzXk", "value": 0}, {"source": "vZ2bO", "target": "lyZ61", "value": 0}, {"source": "8zKEA", "target": "m8eb", "value": 0}, {"source": "eb1e", "target": "ZANE", "value": 0}, {"source": "pKXdl", "target": "NAzXk", "value": 2}, {"source": "pKXdl", "target": "lyZ61", "value": 0}, {"source": "4Wnbq", "target": "jNZal", "value": 1}, {"source": "p0DN", "target": "jN9Nr", "value": 0}, {"source": "QpPR3", "target": "pB11", "value": 0}, {"source": "QpPR3", "target": "QXX3", "value": 0}, {"source": "QpPR3", "target": "AVDr", "value": 0}, {"source": "gXZg", "target": "1jVBk", "value": 0}, {"source": "Z9qEQ", "target": "D9ep", "value": 0}, {"source": "Z9qEQ", "target": "plrgQ", "value": 5}, {"source": "Z9qEQ", "target": "JmyJ5", "value": 0}, {"source": "z9OGK", "target": "jNq8m", "value": 0}, {"source": "z9OGK", "target": "Nb3q0", "value": 0}, {"source": "O45Ey", "target": "VrRb", "value": 0}, {"source": "O45Ey", "target": "BvOmV", "value": 0}, {"source": "O45Ey", "target": "06Zod", "value": 0}, {"source": "O45Ey", "target": "Ewo0o", "value": 0}, {"source": "O45Ey", "target": "oy3PX", "value": 0}, {"source": "O45Ey", "target": "gZmOd", "value": 0}, {"source": "O45Ey", "target": "K3NRz", "value": 2}, {"source": "O45Ey", "target": "vZlPb", "value": 0}, {"source": "O45Ey", "target": "jNZal", "value": 0}, {"source": "O45Ey", "target": "Dmnwa", "value": 0}, {"source": "O45Ey", "target": "kD6Nv", "value": 2}, {"source": "O45Ey", "target": "OaR9", "value": 1}, {"source": "jNpWr", "target": "pB11", "value": 0}, {"source": "jNpWr", "target": "gZBVW", "value": 0}, {"source": "jNpWr", "target": "7VENo", "value": 0}, {"source": "jNpWr", "target": "Ewo0o", "value": 0}, {"source": "jNpWr", "target": "K3NRz", "value": 1}, {"source": "jNpWr", "target": "vZBB9", "value": 0}, {"source": "jNpWr", "target": "oy3PX", "value": 0}, {"source": "jNpWr", "target": "Dmnwa", "value": 0}, {"source": "jNpWr", "target": "54aBr", "value": 0}, {"source": "jNpWr", "target": "vZlPb", "value": 0}, {"source": "jNpWr", "target": "jNZal", "value": 2}, {"source": "jNpWr", "target": "7Vj8b", "value": 0}, {"source": "jNpWr", "target": "vZ42D", "value": 0}, {"source": "jNpWr", "target": "Ew8zB", "value": 0}, {"source": "jNpWr", "target": "D9ep", "value": 0}, {"source": "jNpWr", "target": "aaXA", "value": 0}, {"source": "OaR9", "target": "2RnZ7", "value": 0}, {"source": "OaR9", "target": "WvB5", "value": 0}, {"source": "OaR9", "target": "NA2Na", "value": 0}, {"source": "OaR9", "target": "7VENo", "value": 4}, {"source": "OaR9", "target": "Nb3q0", "value": 0}, {"source": "OaR9", "target": "w8kA", "value": 2}, {"source": "OaR9", "target": "vZlPb", "value": 0}, {"source": "OaR9", "target": "Gk2e", "value": 1}, {"source": "OaR9", "target": "84P2", "value": 0}, {"source": "OaR9", "target": "Gbpd", "value": 0}, {"source": "OaR9", "target": "O45Ey", "value": 1}, {"source": "OaR9", "target": "gZBWl", "value": 1}, {"source": "OaR9", "target": "vZBB9", "value": 2}, {"source": "OaR9", "target": "6Rnw", "value": 0}, {"source": "OaR9", "target": "K3NRz", "value": 1}, {"source": "OaR9", "target": "jNZal", "value": 2}, {"source": "OaR9", "target": "va8O", "value": 2}, {"source": "OaR9", "target": "Ew8zB", "value": 1}, {"source": "OaR9", "target": "kD6Nv", "value": 4}, {"source": "OaR9", "target": "J3j4y", "value": 3}, {"source": "OaR9", "target": "Rvr1", "value": 0}, {"source": "OaR9", "target": "06Zod", "value": 0}, {"source": "OaR9", "target": "27bv", "value": 1}, {"source": "OaR9", "target": "qJ15", "value": 0}, {"source": "RD0W", "target": "ND5J", "value": 0}, {"source": "RD0W", "target": "pAvn", "value": 0}, {"source": "b9kOk", "target": "D9ep", "value": 0}, {"source": "AVDr", "target": "Ewo0o", "value": 0}, {"source": "AVDr", "target": "plrgQ", "value": 0}, {"source": "AVDr", "target": "Z05e", "value": 2}, {"source": "AVDr", "target": "JmyJ5", "value": 1}, {"source": "AVDr", "target": "Dmnwa", "value": 0}, {"source": "AVDr", "target": "D9ep", "value": 0}, {"source": "AVDr", "target": "kD6Nv", "value": 0}, {"source": "8rnwm", "target": "vZBB9", "value": 0}, {"source": "8rnwm", "target": "ZANE", "value": 0}, {"source": "8rnwm", "target": "Q7XK", "value": 0}, {"source": "8rnwm", "target": "Nb3q0", "value": 0}, {"source": "3pKV9", "target": "K3NRz", "value": 0}, {"source": "vZlPb", "target": "O45Ey", "value": 0}, {"source": "vZlPb", "target": "wzrl", "value": 0}, {"source": "vZlPb", "target": "7VENo", "value": 2}, {"source": "vZlPb", "target": "Ewo0o", "value": 0}, {"source": "vZlPb", "target": "27bv", "value": 0}, {"source": "vZlPb", "target": "oy3PX", "value": 0}, {"source": "vZlPb", "target": "gZBWl", "value": 0}, {"source": "vZlPb", "target": "54aBr", "value": 0}, {"source": "vZlPb", "target": "Q7XK", "value": 0}, {"source": "vZlPb", "target": "BA2bD", "value": 0}, {"source": "vZlPb", "target": "O98ez", "value": 0}, {"source": "vZlPb", "target": "84P2", "value": 0}, {"source": "vZlPb", "target": "OaR9", "value": 0}, {"source": "vZlPb", "target": "vZWNb", "value": 0}, {"source": "vZlPb", "target": "Gbpd", "value": 0}, {"source": "QyaO", "target": "ypAyZ", "value": 0}, {"source": "QyaO", "target": "pAvn", "value": 0}, {"source": "QyaO", "target": "eRNNb", "value": 0}, {"source": "QyaO", "target": "vZ2bO", "value": 0}, {"source": "QyaO", "target": "K3NRz", "value": 0}, {"source": "QyaO", "target": "WEpoV", "value": 0}, {"source": "QyaO", "target": "q07yR", "value": 0}, {"source": "QyaO", "target": "NAnpm", "value": 0}, {"source": "nKvXj", "target": "3jJDk", "value": 0}, {"source": "nKvXj", "target": "oy3PX", "value": 0}, {"source": "GPpOo", "target": "oyweQ", "value": 0}, {"source": "GPpOo", "target": "K3NRz", "value": 4}, {"source": "GPpOo", "target": "08Oz", "value": 0}, {"source": "GPpOo", "target": "kD6Nv", "value": 4}, {"source": "GPpOo", "target": "pAvn", "value": 0}, {"source": "BvOmV", "target": "erGw", "value": 0}, {"source": "BvOmV", "target": "2RnZ7", "value": 1}, {"source": "BvOmV", "target": "EweRP", "value": 0}, {"source": "BvOmV", "target": "Z05e", "value": 0}, {"source": "BvOmV", "target": "jNpWr", "value": 0}, {"source": "BvOmV", "target": "Dmnwa", "value": 0}, {"source": "BvOmV", "target": "Ew8zB", "value": 1}, {"source": "BvOmV", "target": "BAb5W", "value": 2}, {"source": "BvOmV", "target": "m8eb", "value": 3}, {"source": "BvOmV", "target": "vZlPb", "value": 0}, {"source": "BvOmV", "target": "zzan", "value": 0}, {"source": "BvOmV", "target": "6nlRe", "value": 0}, {"source": "BvOmV", "target": "BvEBp", "value": 0}, {"source": "BvOmV", "target": "BA2bD", "value": 2}, {"source": "BvOmV", "target": "vZBB9", "value": 0}, {"source": "BvOmV", "target": "qBj55", "value": 1}, {"source": "BvOmV", "target": "K3qlb", "value": 2}, {"source": "BvOmV", "target": "K3NRz", "value": 6}, {"source": "BvOmV", "target": "jNZal", "value": 6}, {"source": "BvOmV", "target": "ErQa", "value": 0}, {"source": "BvOmV", "target": "XJKzK", "value": 0}, {"source": "BvOmV", "target": "Gbpd", "value": 0}, {"source": "BvOmV", "target": "NApZ0", "value": 0}, {"source": "BvOmV", "target": "grz5", "value": 0}, {"source": "BvOmV", "target": "q07yR", "value": 0}, {"source": "GVyww", "target": "QDGnK", "value": 0}, {"source": "qBj55", "target": "BA2bD", "value": 0}, {"source": "qBj55", "target": "BAb5W", "value": 0}, {"source": "qBj55", "target": "BvOmV", "value": 0}, {"source": "qBj55", "target": "7VENo", "value": 0}, {"source": "qBj55", "target": "z9OGK", "value": 0}, {"source": "qBj55", "target": "gZBWl", "value": 0}, {"source": "qBj55", "target": "54aBr", "value": 0}, {"source": "qBj55", "target": "vZBB9", "value": 0}, {"source": "qBj55", "target": "pKaBX", "value": 0}, {"source": "qBj55", "target": "gZmOd", "value": 0}, {"source": "qBj55", "target": "K3NRz", "value": 1}, {"source": "qBj55", "target": "vZlPb", "value": 0}, {"source": "qBj55", "target": "Ew8zB", "value": 0}, {"source": "qBj55", "target": "0jrn3", "value": 0}, {"source": "qBj55", "target": "jNq8m", "value": 0}, {"source": "GP6dK", "target": "jN9Nr", "value": 0}, {"source": "qJ15", "target": "0jrn3", "value": 0}, {"source": "qJ15", "target": "27bv", "value": 0}, {"source": "qJ15", "target": "OaR9", "value": 0}, {"source": "K3NRz", "target": "aVAR", "value": 1}, {"source": "K3NRz", "target": "4Wnbq", "value": 0}, {"source": "K3NRz", "target": "BA2bD", "value": 0}, {"source": "K3NRz", "target": "OaR9", "value": 0}, {"source": "K3NRz", "target": "QpRlR", "value": 0}, {"source": "K3NRz", "target": "3ppvb", "value": 2}, {"source": "K3NRz", "target": "wzrl", "value": 0}, {"source": "K3NRz", "target": "ZANE", "value": 0}, {"source": "K3NRz", "target": "vZlPb", "value": 0}, {"source": "K3NRz", "target": "GPpOo", "value": 0}, {"source": "K3NRz", "target": "GVADo", "value": 0}, {"source": "K3NRz", "target": "WvB5", "value": 0}, {"source": "K3NRz", "target": "BvOmV", "value": 0}, {"source": "K3NRz", "target": "ypAyZ", "value": 0}, {"source": "K3NRz", "target": "6Rnw", "value": 0}, {"source": "K3NRz", "target": "BAb5W", "value": 0}, {"source": "K3NRz", "target": "gpDzZ", "value": 0}, {"source": "K3NRz", "target": "El8g", "value": 0}, {"source": "K3NRz", "target": "jNZal", "value": 0}, {"source": "K3NRz", "target": "Ew8zB", "value": 0}, {"source": "K3NRz", "target": "RADPG", "value": 0}, {"source": "K3NRz", "target": "kD6Nv", "value": 1}, {"source": "K3NRz", "target": "Gbpd", "value": 0}, {"source": "K3NRz", "target": "q07yR", "value": 0}, {"source": "dBK0w", "target": "Ewo0o", "value": 0}, {"source": "O4Bk9", "target": "K3NRz", "value": 0}, {"source": "O4Bk9", "target": "NAzXk", "value": 0}, {"source": "vZ42D", "target": "pB11", "value": 0}, {"source": "vZ42D", "target": "oy3PX", "value": 0}, {"source": "vZ42D", "target": "jNpWr", "value": 0}, {"source": "vZ42D", "target": "aJVv", "value": 0}, {"source": "vZWNb", "target": "vZlPb", "value": 0}, {"source": "plmPn", "target": "qnJ7", "value": 0}, {"source": "2RoaP", "target": "vZlPb", "value": 0}, {"source": "zJrw", "target": "vZBB9", "value": 0}, {"source": "zJrw", "target": "3ppvb", "value": 0}, {"source": "zJrw", "target": "jNZal", "value": 0}, {"source": "GP7dK", "target": "JmyJ5", "value": 0}, {"source": "jNlNl", "target": "X9aDe", "value": 0}, {"source": "jNmwG", "target": "Nb3q0", "value": 0}, {"source": "BA2bD", "target": "BAb5W", "value": 0}, {"source": "BA2bD", "target": "BvOmV", "value": 1}, {"source": "BA2bD", "target": "2RnZ7", "value": 0}, {"source": "BA2bD", "target": "K3NRz", "value": 1}, {"source": "BA2bD", "target": "vZBB9", "value": 1}, {"source": "BA2bD", "target": "O94g1", "value": 0}, {"source": "BA2bD", "target": "EweRP", "value": 0}, {"source": "BA2bD", "target": "plrgQ", "value": 3}, {"source": "BA2bD", "target": "gZmOd", "value": 1}, {"source": "BA2bD", "target": "JmyJ5", "value": 2}, {"source": "BA2bD", "target": "jN9Nr", "value": 0}, {"source": "BA2bD", "target": "vZlPb", "value": 2}, {"source": "BA2bD", "target": "jNZal", "value": 1}, {"source": "BA2bD", "target": "m8eb", "value": 0}, {"source": "BA2bD", "target": "06r96", "value": 1}, {"source": "BA2bD", "target": "D9ep", "value": 1}, {"source": "BA2bD", "target": "qBj55", "value": 0}, {"source": "BA2bD", "target": "gZa1d", "value": 0}, {"source": "GVa2K", "target": "GP7dK", "value": 0}, {"source": "BvOP0", "target": "1KOE", "value": 0}, {"source": "7wk3", "target": "7VENo", "value": 0}, {"source": "7wk3", "target": "J3j4y", "value": 0}, {"source": "7wk3", "target": "Z9XD4", "value": 0}, {"source": "7wk3", "target": "54aBr", "value": 0}, {"source": "7wk3", "target": "yzGJ", "value": 2}, {"source": "7wk3", "target": "D9ep", "value": 0}, {"source": "7wk3", "target": "84P2", "value": 0}, {"source": "WEyVQ", "target": "pKaBX", "value": 0}, {"source": "QDZrO", "target": "7VENo", "value": 0}, {"source": "jNq8m", "target": "7VENo", "value": 2}, {"source": "jNq8m", "target": "Nb3q0", "value": 0}, {"source": "jNq8m", "target": "27bv", "value": 1}, {"source": "jNq8m", "target": "kD6Nv", "value": 1}, {"source": "jNq8m", "target": "qBj55", "value": 1}, {"source": "jNq8m", "target": "06Zod", "value": 0}, {"source": "jNq8m", "target": "gZmOd", "value": 1}, {"source": "jNq8m", "target": "pAvn", "value": 0}, {"source": "jNq8m", "target": "Wqol5", "value": 0}, {"source": "jNq8m", "target": "K3NRz", "value": 0}, {"source": "jNq8m", "target": "vZlPb", "value": 0}, {"source": "jNq8m", "target": "3jzya", "value": 1}, {"source": "jNq8m", "target": "4W2W9", "value": 0}, {"source": "jNq8m", "target": "Ew8zB", "value": 0}, {"source": "jNq8m", "target": "rKdr7", "value": 1}, {"source": "jNq8m", "target": "6rdD", "value": 0}, {"source": "jNq8m", "target": "z9OGK", "value": 0}, {"source": "gpvad", "target": "7VENo", "value": 0}, {"source": "QDBDD", "target": "Ewo0o", "value": 0}, {"source": "Dmnwa", "target": "Z05e", "value": 1}, {"source": "Dmnwa", "target": "jNpWr", "value": 0}, {"source": "Dmnwa", "target": "NA2Na", "value": 0}, {"source": "Dmnwa", "target": "Nb3q0", "value": 1}, {"source": "Dmnwa", "target": "1jVBk", "value": 0}, {"source": "Dmnwa", "target": "vZlPb", "value": 0}, {"source": "Dmnwa", "target": "QD3BE", "value": 0}, {"source": "Dmnwa", "target": "O45Ey", "value": 0}, {"source": "Dmnwa", "target": "BvEBp", "value": 0}, {"source": "Dmnwa", "target": "BvOmV", "value": 1}, {"source": "Dmnwa", "target": "gZBWl", "value": 0}, {"source": "Dmnwa", "target": "JmyJ5", "value": 0}, {"source": "Dmnwa", "target": "K3NRz", "value": 3}, {"source": "Dmnwa", "target": "jNZal", "value": 3}, {"source": "Dmnwa", "target": "ErQa", "value": 0}, {"source": "Dmnwa", "target": "va8O", "value": 0}, {"source": "Dmnwa", "target": "kD6Nv", "value": 0}, {"source": "Dmnwa", "target": "aaXA", "value": 0}, {"source": "Dmnwa", "target": "p0DN", "value": 0}, {"source": "Dmnwa", "target": "Qbro", "value": 0}, {"source": "Dmnwa", "target": "27bv", "value": 0}, {"source": "b7P6", "target": "790o", "value": 1}, {"source": "b7P6", "target": "J6k5", "value": 0}, {"source": "b7P6", "target": "O94g1", "value": 0}, {"source": "b7P6", "target": "EweRP", "value": 0}, {"source": "b7P6", "target": "plrgQ", "value": 0}, {"source": "b7P6", "target": "Z05e", "value": 0}, {"source": "b7P6", "target": "Dmnwa", "value": 0}, {"source": "b7P6", "target": "OaR9", "value": 0}, {"source": "b7P6", "target": "WvB5", "value": 1}, {"source": "b7P6", "target": "AlgDJ", "value": 0}, {"source": "b7P6", "target": "BAb5W", "value": 0}, {"source": "b7P6", "target": "J3j4y", "value": 0}, {"source": "b7P6", "target": "GVOGK", "value": 0}, {"source": "b7P6", "target": "ZANE", "value": 0}, {"source": "b7P6", "target": "Wqol5", "value": 0}, {"source": "b7P6", "target": "1jVBk", "value": 0}, {"source": "b7P6", "target": "v2jOz", "value": 0}, {"source": "b7P6", "target": "BvEBp", "value": 0}, {"source": "b7P6", "target": "gZBWl", "value": 1}, {"source": "b7P6", "target": "eRNNb", "value": 0}, {"source": "b7P6", "target": "El8g", "value": 0}, {"source": "b7P6", "target": "K3NRz", "value": 1}, {"source": "b7P6", "target": "jNZal", "value": 0}, {"source": "b7P6", "target": "va8O", "value": 0}, {"source": "b7P6", "target": "pAvn", "value": 0}, {"source": "b7P6", "target": "jZBDN", "value": 0}, {"source": "b7P6", "target": "06Zod", "value": 0}, {"source": "b7P6", "target": "Qbro", "value": 0}, {"source": "b7P6", "target": "pKaBX", "value": 0}, {"source": "b7P6", "target": "w8kA", "value": 0}, {"source": "b7P6", "target": "27bv", "value": 2}, {"source": "NAEvq", "target": "mXkb", "value": 0}, {"source": "ZANE", "target": "wyRlO", "value": 0}, {"source": "ZANE", "target": "7VENo", "value": 2}, {"source": "ZANE", "target": "Qbro", "value": 0}, {"source": "ZANE", "target": "06Zod", "value": 0}, {"source": "ZANE", "target": "z2OGw", "value": 0}, {"source": "ZANE", "target": "vZBB9", "value": 0}, {"source": "ZANE", "target": "vZlPb", "value": 1}, {"source": "ZANE", "target": "NAzXk", "value": 0}, {"source": "ZANE", "target": "3jJDk", "value": 0}, {"source": "ZANE", "target": "b7P6", "value": 1}, {"source": "ZANE", "target": "grz5", "value": 1}, {"source": "6nlRe", "target": "WvB5", "value": 0}, {"source": "6nlRe", "target": "3jJDk", "value": 1}, {"source": "6nlRe", "target": "BvEBp", "value": 0}, {"source": "6nlRe", "target": "7VENo", "value": 0}, {"source": "06r96", "target": "BA2bD", "value": 0}, {"source": "06r96", "target": "27bv", "value": 1}, {"source": "06r96", "target": "vZBB9", "value": 1}, {"source": "06r96", "target": "K3NRz", "value": 0}, {"source": "06r96", "target": "jNZal", "value": 0}, {"source": "06r96", "target": "7Vj8b", "value": 0}, {"source": "J3wOA", "target": "2Rb1p", "value": 0}, {"source": "Rvr1", "target": "BvEBp", "value": 0}, {"source": "Rvr1", "target": "vZ79R", "value": 0}, {"source": "Rvr1", "target": "OaR9", "value": 0}, {"source": "nOK6O", "target": "oy3PX", "value": 0}, {"source": "nOK6O", "target": "0jed9", "value": 0}, {"source": "27bv", "target": "7Vj8b", "value": 0}, {"source": "27bv", "target": "J6k5", "value": 1}, {"source": "27bv", "target": "oy3PX", "value": 0}, {"source": "27bv", "target": "Z05e", "value": 0}, {"source": "27bv", "target": "wzrl", "value": 0}, {"source": "27bv", "target": "va8O", "value": 0}, {"source": "27bv", "target": "3jJDk", "value": 0}, {"source": "27bv", "target": "OaR9", "value": 1}, {"source": "27bv", "target": "WvB5", "value": 1}, {"source": "27bv", "target": "BAb5W", "value": 0}, {"source": "27bv", "target": "7VENo", "value": 1}, {"source": "27bv", "target": "J3j4y", "value": 0}, {"source": "27bv", "target": "w8kA", "value": 0}, {"source": "27bv", "target": "jN9Nr", "value": 0}, {"source": "27bv", "target": "QDJ4D", "value": 0}, {"source": "27bv", "target": "gZmOd", "value": 0}, {"source": "27bv", "target": "pAvn", "value": 0}, {"source": "27bv", "target": "1jVBk", "value": 0}, {"source": "27bv", "target": "Q7XK", "value": 0}, {"source": "27bv", "target": "4W2W9", "value": 0}, {"source": "27bv", "target": "84P2", "value": 0}, {"source": "27bv", "target": "qJ15", "value": 0}, {"source": "27bv", "target": "gZBWl", "value": 0}, {"source": "27bv", "target": "vZBB9", "value": 0}, {"source": "27bv", "target": "6Rnw", "value": 0}, {"source": "27bv", "target": "ebZ9", "value": 0}, {"source": "27bv", "target": "Algmq", "value": 0}, {"source": "27bv", "target": "K3NRz", "value": 0}, {"source": "27bv", "target": "EqaG", "value": 0}, {"source": "27bv", "target": "jNZal", "value": 1}, {"source": "27bv", "target": "vZlPb", "value": 1}, {"source": "27bv", "target": "06r96", "value": 1}, {"source": "27bv", "target": "aaXA", "value": 0}, {"source": "27bv", "target": "pB11", "value": 0}, {"source": "27bv", "target": "pKaBX", "value": 0}, {"source": "27bv", "target": "jNq8m", "value": 0}, {"source": "27bv", "target": "6rdD", "value": 0}, {"source": "27bv", "target": "NAzXk", "value": 0}, {"source": "8rEvG", "target": "Ewo0o", "value": 0}, {"source": "O94g1", "target": "NAz4J", "value": 0}, {"source": "O94g1", "target": "AlgDJ", "value": 0}, {"source": "O94g1", "target": "7Vj8b", "value": 0}, {"source": "O94g1", "target": "Ewo0o", "value": 0}, {"source": "O94g1", "target": "QDJ4D", "value": 0}, {"source": "O94g1", "target": "K3NRz", "value": 0}, {"source": "O94g1", "target": "jNpWr", "value": 0}, {"source": "O94g1", "target": "vZlPb", "value": 0}, {"source": "O94g1", "target": "wzrl", "value": 1}, {"source": "ypvbJ", "target": "4Z9e", "value": 0}, {"source": "plrgQ", "target": "7Vj8b", "value": 0}, {"source": "plrgQ", "target": "oy3PX", "value": 0}, {"source": "plrgQ", "target": "Z05e", "value": 2}, {"source": "plrgQ", "target": "EWZeo", "value": 1}, {"source": "plrgQ", "target": "1KOE", "value": 0}, {"source": "plrgQ", "target": "8r3By", "value": 0}, {"source": "plrgQ", "target": "J3j4y", "value": 0}, {"source": "plrgQ", "target": "GP7dK", "value": 0}, {"source": "plrgQ", "target": "Q7XK", "value": 0}, {"source": "plrgQ", "target": "QD3BE", "value": 0}, {"source": "plrgQ", "target": "JA1A", "value": 0}, {"source": "plrgQ", "target": "BA2bD", "value": 4}, {"source": "plrgQ", "target": "AVDr", "value": 0}, {"source": "plrgQ", "target": "JmyJ5", "value": 1}, {"source": "plrgQ", "target": "jNZal", "value": 0}, {"source": "plrgQ", "target": "va8O", "value": 1}, {"source": "plrgQ", "target": "XJKzK", "value": 0}, {"source": "plrgQ", "target": "Vj3gv", "value": 0}, {"source": "plrgQ", "target": "eb1e", "value": 0}, {"source": "plrgQ", "target": "3jzya", "value": 3}, {"source": "plrgQ", "target": "X9rGX", "value": 1}, {"source": "plrgQ", "target": "rKdr7", "value": 0}, {"source": "plrgQ", "target": "Z9qEQ", "value": 0}, {"source": "dBVl1", "target": "rKdr7", "value": 0}, {"source": "QpRlR", "target": "BAb5W", "value": 0}, {"source": "QpRlR", "target": "oy3PX", "value": 1}, {"source": "QpRlR", "target": "O4Bk9", "value": 0}, {"source": "QpRlR", "target": "K3NRz", "value": 2}, {"source": "QpRlR", "target": "rKdr7", "value": 0}, {"source": "QpRlR", "target": "D9ep", "value": 0}, {"source": "QpRlR", "target": "OaR9", "value": 0}, {"source": "GPnnd", "target": "NA2Na", "value": 0}, {"source": "gZmOd", "target": "pB11", "value": 0}, {"source": "gZmOd", "target": "BvEBp", "value": 0}, {"source": "gZmOd", "target": "7VENo", "value": 1}, {"source": "gZmOd", "target": "wzrl", "value": 0}, {"source": "gZmOd", "target": "K3NRz", "value": 0}, {"source": "gZmOd", "target": "vZBB9", "value": 0}, {"source": "gZmOd", "target": "pKaBX", "value": 0}, {"source": "gZmOd", "target": "wyv9v", "value": 0}, {"source": "gZmOd", "target": "rKdr7", "value": 1}, {"source": "gZmOd", "target": "vZlPb", "value": 2}, {"source": "gZmOd", "target": "27bv", "value": 0}, {"source": "gZmOd", "target": "0jrn3", "value": 0}, {"source": "gZmOd", "target": "jNq8m", "value": 0}, {"source": "gZmOd", "target": "OaR9", "value": 0}, {"source": "GyD3", "target": "O94g1", "value": 0}, {"source": "GyD3", "target": "oy3PX", "value": 0}, {"source": "GyD3", "target": "Ewo0o", "value": 0}, {"source": "GyD3", "target": "jNq8m", "value": 0}, {"source": "gZa1d", "target": "NA2Na", "value": 0}, {"source": "gZa1d", "target": "BvEBp", "value": 0}, {"source": "gZa1d", "target": "Nb3q0", "value": 0}, {"source": "gZa1d", "target": "jN9Nr", "value": 0}, {"source": "gZa1d", "target": "pKaBX", "value": 2}, {"source": "gZa1d", "target": "m8eb", "value": 0}, {"source": "gZa1d", "target": "vZlPb", "value": 0}, {"source": "gZa1d", "target": "4W2W9", "value": 0}, {"source": "gZa1d", "target": "0jrn3", "value": 0}, {"source": "gZa1d", "target": "rKdr7", "value": 0}, {"source": "gZa1d", "target": "D9ep", "value": 0}, {"source": "gZa1d", "target": "vZ79R", "value": 0}, {"source": "gZa1d", "target": "v2jOz", "value": 0}, {"source": "gZa1d", "target": "J3j4y", "value": 1}, {"source": "3jW1J", "target": "1jVBk", "value": 0}, {"source": "pKaBX", "target": "BvEBp", "value": 0}, {"source": "pKaBX", "target": "wzrl", "value": 0}, {"source": "pKaBX", "target": "Alr5l", "value": 0}, {"source": "pKaBX", "target": "eRNNb", "value": 0}, {"source": "pKaBX", "target": "Z05e", "value": 1}, {"source": "pKaBX", "target": "27bv", "value": 0}, {"source": "pKaBX", "target": "gZmOd", "value": 0}, {"source": "pKaBX", "target": "wyv9v", "value": 0}, {"source": "pKaBX", "target": "Wqol5", "value": 0}, {"source": "pKaBX", "target": "54aBr", "value": 0}, {"source": "pKaBX", "target": "jNpWr", "value": 0}, {"source": "pKaBX", "target": "DmWzd", "value": 0}, {"source": "pKaBX", "target": "NAzXk", "value": 1}, {"source": "pKaBX", "target": "QyaO", "value": 0}, {"source": "pKaBX", "target": "0jrn3", "value": 0}, {"source": "pKaBX", "target": "3j34a", "value": 1}, {"source": "pKaBX", "target": "84P2", "value": 0}, {"source": "pKaBX", "target": "gZa1d", "value": 1}, {"source": "q0gXm", "target": "7VENo", "value": 0}, {"source": "q0gXm", "target": "Ewo0o", "value": 0}, {"source": "q0gXm", "target": "oy3PX", "value": 0}, {"source": "q0gXm", "target": "gZmOd", "value": 1}, {"source": "q0gXm", "target": "JmyJ5", "value": 1}, {"source": "q0gXm", "target": "K3NRz", "value": 0}, {"source": "q0gXm", "target": "vZlPb", "value": 3}, {"source": "q0gXm", "target": "jNZal", "value": 0}, {"source": "q0gXm", "target": "X9aDe", "value": 0}, {"source": "q0gXm", "target": "0jrn3", "value": 0}, {"source": "q0gXm", "target": "84P2", "value": 0}, {"source": "q0gXm", "target": "kD6Nv", "value": 2}, {"source": "q0gXm", "target": "OaR9", "value": 0}, {"source": "2B87", "target": "pAvn", "value": 0}, {"source": "JegB", "target": "NAzXk", "value": 0}, {"source": "DmWzd", "target": "Ew8zB", "value": 0}, {"source": "DmWzd", "target": "X9aDe", "value": 0}, {"source": "DmWzd", "target": "K3NRz", "value": 0}, {"source": "1KOE", "target": "K602", "value": 0}, {"source": "1KOE", "target": "plrgQ", "value": 0}, {"source": "1KOE", "target": "J3lAK", "value": 0}, {"source": "1KOE", "target": "Q2Ko", "value": 0}, {"source": "1KOE", "target": "mj3X3", "value": 0}, {"source": "D9ep", "target": "BA2bD", "value": 0}, {"source": "GVOGK", "target": "1jVBk", "value": 0}, {"source": "84P2", "target": "pKXan", "value": 0}, {"source": "84P2", "target": "Z05e", "value": 2}, {"source": "84P2", "target": "rKpXO", "value": 0}, {"source": "84P2", "target": "jNpWr", "value": 0}, {"source": "84P2", "target": "OaR9", "value": 1}, {"source": "84P2", "target": "BAb5W", "value": 0}, {"source": "84P2", "target": "pAvn", "value": 0}, {"source": "84P2", "target": "w8kA", "value": 0}, {"source": "84P2", "target": "vZlPb", "value": 0}, {"source": "84P2", "target": "vZ79R", "value": 1}, {"source": "84P2", "target": "QpPR3", "value": 0}, {"source": "84P2", "target": "gZBWl", "value": 0}, {"source": "84P2", "target": "K3NRz", "value": 1}, {"source": "84P2", "target": "jNZal", "value": 1}, {"source": "84P2", "target": "va8O", "value": 2}, {"source": "84P2", "target": "RzA1", "value": 0}, {"source": "84P2", "target": "J3j4y", "value": 2}, {"source": "84P2", "target": "pB11", "value": 0}, {"source": "84P2", "target": "06Zod", "value": 1}, {"source": "84P2", "target": "Jjkp", "value": 0}, {"source": "84P2", "target": "NApZ0", "value": 2}, {"source": "84P2", "target": "Qpmen", "value": 0}, {"source": "84P2", "target": "27bv", "value": 0}, {"source": "O4Pw2", "target": "vZBB9", "value": 0}, {"source": "O4Pw2", "target": "jNZal", "value": 0}, {"source": "O4Pw2", "target": "JmyJ5", "value": 0}, {"source": "9Gd50", "target": "JmyJ5", "value": 2}, {"source": "54aBr", "target": "pKaBX", "value": 0}, {"source": "54aBr", "target": "Algmq", "value": 0}, {"source": "54aBr", "target": "vZWNb", "value": 0}, {"source": "54aBr", "target": "Nb3q0", "value": 1}, {"source": "ErQa", "target": "BvOmV", "value": 0}, {"source": "va8O", "target": "WvB5", "value": 0}, {"source": "va8O", "target": "BAb5W", "value": 1}, {"source": "va8O", "target": "7VENo", "value": 3}, {"source": "va8O", "target": "Nb3q0", "value": 1}, {"source": "va8O", "target": "gZBWl", "value": 2}, {"source": "va8O", "target": "vZBB9", "value": 2}, {"source": "va8O", "target": "ebZ9", "value": 1}, {"source": "va8O", "target": "plrgQ", "value": 2}, {"source": "va8O", "target": "Z05e", "value": 1}, {"source": "va8O", "target": "pAvn", "value": 0}, {"source": "va8O", "target": "JmyJ5", "value": 2}, {"source": "va8O", "target": "K3NRz", "value": 1}, {"source": "va8O", "target": "vZlPb", "value": 0}, {"source": "va8O", "target": "jNZal", "value": 6}, {"source": "va8O", "target": "27bv", "value": 1}, {"source": "va8O", "target": "Ew8zB", "value": 1}, {"source": "va8O", "target": "84P2", "value": 2}, {"source": "va8O", "target": "kD6Nv", "value": 0}, {"source": "va8O", "target": "QDJ4D", "value": 0}, {"source": "va8O", "target": "OaR9", "value": 2}, {"source": "jZBDN", "target": "K3NRz", "value": 0}, {"source": "dBvVK", "target": "NAz4J", "value": 0}, {"source": "dBvVK", "target": "JegB", "value": 0}, {"source": "dBvVK", "target": "vZBB9", "value": 0}, {"source": "dBvVK", "target": "K3NRz", "value": 1}, {"source": "dBvVK", "target": "Ew8zB", "value": 1}, {"source": "dBvVK", "target": "7VENo", "value": 0}, {"source": "Ew8zB", "target": "7VENo", "value": 0}, {"source": "Ew8zB", "target": "jNlNl", "value": 0}, {"source": "Ew8zB", "target": "vZBB9", "value": 1}, {"source": "Ew8zB", "target": "6Rnw", "value": 0}, {"source": "Ew8zB", "target": "El8g", "value": 0}, {"source": "Ew8zB", "target": "K3NRz", "value": 2}, {"source": "Ew8zB", "target": "vZlPb", "value": 0}, {"source": "Ew8zB", "target": "dBvVK", "value": 0}, {"source": "Ew8zB", "target": "OaR9", "value": 1}, {"source": "vEZd", "target": "9gKD", "value": 0}, {"source": "w5eK", "target": "NAzXk", "value": 0}, {"source": "XJ74A", "target": "Dmnwa", "value": 0}, {"source": "z2vKy", "target": "QDbvn", "value": 0}, {"source": "z2vKy", "target": "Nb3q0", "value": 0}, {"source": "z2vKy", "target": "JmyJ5", "value": 2}, {"source": "q07yR", "target": "kD6Nv", "value": 0}, {"source": "AlNg0", "target": "84P2", "value": 0}, {"source": "dBAdN", "target": "Ew8zB", "value": 0}, {"source": "Ewo0o", "target": "7VENo", "value": 0}, {"source": "Ewo0o", "target": "J3j4y", "value": 0}, {"source": "Ewo0o", "target": "vZBB9", "value": 0}, {"source": "Ewo0o", "target": "m8eb", "value": 0}, {"source": "Ewo0o", "target": "lypB1", "value": 0}, {"source": "Ewo0o", "target": "Q2Ko", "value": 0}, {"source": "Ewo0o", "target": "JmyJ5", "value": 0}, {"source": "Ewo0o", "target": "lNd3m", "value": 0}, {"source": "GVO86", "target": "oy3PX", "value": 0}, {"source": "GVO86", "target": "vZlPb", "value": 0}, {"source": "4lJZ", "target": "K3NRz", "value": 2}, {"source": "4lJZ", "target": "BAb5W", "value": 0}, {"source": "4lJZ", "target": "oy3PX", "value": 0}, {"source": "yzGJ", "target": "7wk3", "value": 0}, {"source": "J3j4y", "target": "wzrl", "value": 0}, {"source": "J3j4y", "target": "Ewo0o", "value": 0}, {"source": "J3j4y", "target": "27bv", "value": 0}, {"source": "J3j4y", "target": "ebZ9", "value": 0}, {"source": "J3j4y", "target": "plrgQ", "value": 0}, {"source": "J3j4y", "target": "dB4dN", "value": 0}, {"source": "J3j4y", "target": "06r96", "value": 0}, {"source": "J3j4y", "target": "3jJDk", "value": 0}, {"source": "J3j4y", "target": "84P2", "value": 2}, {"source": "J3j4y", "target": "OaR9", "value": 4}, {"source": "J3j4y", "target": "qJ15", "value": 0}, {"source": "dKrv", "target": "wyv9v", "value": 0}, {"source": "QDJ4D", "target": "Gk2e", "value": 0}, {"source": "QDJ4D", "target": "oy3PX", "value": 0}, {"source": "QDJ4D", "target": "gZBWl", "value": 0}, {"source": "vWD9", "target": "ebZ9", "value": 0}, {"source": "w8kA", "target": "gZBWl", "value": 0}, {"source": "w8kA", "target": "OaR9", "value": 1}, {"source": "ND5J", "target": "plrgQ", "value": 0}, {"source": "ND5J", "target": "JmyJ5", "value": 1}, {"source": "Q2Ko", "target": "pB11", "value": 0}, {"source": "Q2Ko", "target": "NAz4J", "value": 0}, {"source": "Q2Ko", "target": "BvEBp", "value": 0}, {"source": "Q2Ko", "target": "7VENo", "value": 1}, {"source": "Q2Ko", "target": "Ewo0o", "value": 1}, {"source": "Q2Ko", "target": "lyZ61", "value": 0}, {"source": "Q2Ko", "target": "ZANE", "value": 0}, {"source": "Q2Ko", "target": "jN9Nr", "value": 0}, {"source": "Q2Ko", "target": "vZlPb", "value": 0}, {"source": "Q2Ko", "target": "1KOE", "value": 0}, {"source": "Q2Ko", "target": "Nb3q0", "value": 0}, {"source": "BvEBp", "target": "Rvr1", "value": 0}, {"source": "BvEBp", "target": "7VENo", "value": 0}, {"source": "BvEBp", "target": "qBqo9", "value": 0}, {"source": "BvEBp", "target": "gZmOd", "value": 0}, {"source": "BvEBp", "target": "n9l7", "value": 1}, {"source": "BvEBp", "target": "m8eb", "value": 1}, {"source": "BvEBp", "target": "Wqol5", "value": 0}, {"source": "BvEBp", "target": "Q2Ko", "value": 0}, {"source": "BvEBp", "target": "3jJDk", "value": 0}, {"source": "BvEBp", "target": "84P2", "value": 0}, {"source": "BvEBp", "target": "v2jOz", "value": 0}, {"source": "X9P2p", "target": "WvB5", "value": 1}, {"source": "X9P2p", "target": "plrgQ", "value": 0}, {"source": "X9P2p", "target": "Z05e", "value": 0}, {"source": "X9P2p", "target": "NApZ0", "value": 0}, {"source": "X9P2p", "target": "K3NRz", "value": 0}, {"source": "X9P2p", "target": "JmyJ5", "value": 2}, {"source": "X9P2p", "target": "jNq8m", "value": 0}, {"source": "ypv3P", "target": "eREry", "value": 0}, {"source": "ypv3P", "target": "06gP3", "value": 0}, {"source": "ypv3P", "target": "QpR5O", "value": 0}, {"source": "z2v34", "target": "vpN4", "value": 0}, {"source": "z95p6", "target": "7VENo", "value": 0}, {"source": "GV7a6", "target": "G5Jo", "value": 0}, {"source": "06Zod", "target": "7VENo", "value": 1}, {"source": "06Zod", "target": "Ewo0o", "value": 0}, {"source": "06Zod", "target": "vZBB9", "value": 0}, {"source": "06Zod", "target": "EweRP", "value": 0}, {"source": "06Zod", "target": "gZmOd", "value": 0}, {"source": "06Zod", "target": "pAvn", "value": 0}, {"source": "06Zod", "target": "K3NRz", "value": 1}, {"source": "06Zod", "target": "jNpWr", "value": 0}, {"source": "06Zod", "target": "rKdr7", "value": 0}, {"source": "06Zod", "target": "jNZal", "value": 0}, {"source": "06Zod", "target": "0jrn3", "value": 0}, {"source": "06Zod", "target": "84P2", "value": 1}, {"source": "06Zod", "target": "QDVbK", "value": 0}, {"source": "06Zod", "target": "kD6Nv", "value": 2}, {"source": "06Zod", "target": "z9OGK", "value": 0}, {"source": "Qpmen", "target": "NA2Na", "value": 0}, {"source": "Qpmen", "target": "7VENo", "value": 0}, {"source": "Qpmen", "target": "pAvn", "value": 0}, {"source": "Qpmen", "target": "gZBWl", "value": 0}, {"source": "Qpmen", "target": "vZBB9", "value": 0}, {"source": "Qpmen", "target": "27bv", "value": 0}, {"source": "Qpmen", "target": "K3NRz", "value": 0}, {"source": "Qpmen", "target": "EqaG", "value": 0}, {"source": "Qpmen", "target": "jNZal", "value": 2}, {"source": "Qpmen", "target": "va8O", "value": 0}, {"source": "Qpmen", "target": "Ew8zB", "value": 0}, {"source": "Qpmen", "target": "84P2", "value": 1}, {"source": "Qpmen", "target": "6rdD", "value": 0}, {"source": "8zkdm", "target": "Ewo0o", "value": 0}, {"source": "7Vj8b", "target": "jNpWr", "value": 1}, {"source": "6Wge", "target": "Ewo0o", "value": 0}, {"source": "aVAR", "target": "7VENo", "value": 1}, {"source": "aVAR", "target": "J3j4y", "value": 0}, {"source": "aVAR", "target": "2RnZ7", "value": 1}, {"source": "aVAR", "target": "27bv", "value": 0}, {"source": "aVAR", "target": "K3NRz", "value": 1}, {"source": "aVAR", "target": "rKdr7", "value": 0}, {"source": "aVAR", "target": "jNZal", "value": 0}, {"source": "eWRy", "target": "pKaBX", "value": 0}, {"source": "eWRy", "target": "gZmOd", "value": 0}, {"source": "a7yDp", "target": "vZBB9", "value": 0}, {"source": "a7yDp", "target": "Ew8zB", "value": 0}, {"source": "a7yDp", "target": "BAb5W", "value": 0}, {"source": "a7yDp", "target": "m8eb", "value": 0}, {"source": "a7yDp", "target": "dKrv", "value": 0}, {"source": "NAnpm", "target": "7Vj8b", "value": 0}, {"source": "NAnpm", "target": "eRNNb", "value": 0}, {"source": "NAnpm", "target": "Z05e", "value": 0}, {"source": "NAnpm", "target": "Wqol5", "value": 1}, {"source": "NAnpm", "target": "r1Xr", "value": 0}, {"source": "NAnpm", "target": "vZlPb", "value": 0}, {"source": "Vjlz6", "target": "XD1y", "value": 0}, {"source": "Alr5l", "target": "7VENo", "value": 1}, {"source": "Alr5l", "target": "O4vdj", "value": 0}, {"source": "Alr5l", "target": "ZANE", "value": 0}, {"source": "Alr5l", "target": "oy3PX", "value": 0}, {"source": "Alr5l", "target": "K3NRz", "value": 0}, {"source": "Alr5l", "target": "rKdr7", "value": 0}, {"source": "Alr5l", "target": "4W2W9", "value": 0}, {"source": "Alr5l", "target": "gZa1d", "value": 0}, {"source": "Alr5l", "target": "wzrl", "value": 0}, {"source": "r92Q", "target": "vZBB9", "value": 0}, {"source": "r92Q", "target": "D9ep", "value": 0}, {"source": "D2yP", "target": "grz5", "value": 0}, {"source": "4npG", "target": "gZXnW", "value": 0}, {"source": "A47a5", "target": "pB11", "value": 0}, {"source": "DmGz0", "target": "7VENo", "value": 0}, {"source": "zzan", "target": "1jVBk", "value": 0}, {"source": "zzan", "target": "vZlPb", "value": 0}, {"source": "vZBB9", "target": "JegB", "value": 0}, {"source": "vZBB9", "target": "Ewo0o", "value": 0}, {"source": "vZBB9", "target": "2RnZ7", "value": 0}, {"source": "vZBB9", "target": "oy3PX", "value": 1}, {"source": "vZBB9", "target": "Z05e", "value": 1}, {"source": "vZBB9", "target": "06r96", "value": 0}, {"source": "vZBB9", "target": "jNpWr", "value": 0}, {"source": "vZBB9", "target": "ypvqZ", "value": 0}, {"source": "vZBB9", "target": "a7yDp", "value": 0}, {"source": "vZBB9", "target": "b9NZw", "value": 0}, {"source": "vZBB9", "target": "OaR9", "value": 2}, {"source": "vZBB9", "target": "7VENo", "value": 3}, {"source": "vZBB9", "target": "pAvn", "value": 0}, {"source": "vZBB9", "target": "Alr5l", "value": 0}, {"source": "vZBB9", "target": "ZANE", "value": 0}, {"source": "vZBB9", "target": "zJrw", "value": 0}, {"source": "vZBB9", "target": "4W3JZ", "value": 0}, {"source": "vZBB9", "target": "gZmOd", "value": 0}, {"source": "vZBB9", "target": "8rnwm", "value": 0}, {"source": "vZBB9", "target": "m8eb", "value": 0}, {"source": "vZBB9", "target": "vZlPb", "value": 1}, {"source": "vZBB9", "target": "84P2", "value": 0}, {"source": "vZBB9", "target": "BA2bD", "value": 0}, {"source": "vZBB9", "target": "gZBWl", "value": 0}, {"source": "vZBB9", "target": "eRNNb", "value": 0}, {"source": "vZBB9", "target": "qBj55", "value": 0}, {"source": "vZBB9", "target": "K3NRz", "value": 0}, {"source": "vZBB9", "target": "jNZal", "value": 2}, {"source": "vZBB9", "target": "va8O", "value": 0}, {"source": "vZBB9", "target": "Ew8zB", "value": 1}, {"source": "vZBB9", "target": "kD6Nv", "value": 1}, {"source": "vZBB9", "target": "06Zod", "value": 0}, {"source": "vZBB9", "target": "dBvVK", "value": 0}, {"source": "vZBB9", "target": "pKaBX", "value": 0}, {"source": "vZBB9", "target": "Qpmen", "value": 0}, {"source": "vZBB9", "target": "27bv", "value": 0}, {"source": "a7ld3", "target": "kD6Nv", "value": 0}, {"source": "a7ld3", "target": "Nb3q0", "value": 0}, {"source": "lBzp", "target": "oy3PX", "value": 0}, {"source": "JmyJ5", "target": "Ewo0o", "value": 0}, {"source": "JmyJ5", "target": "oy3PX", "value": 0}, {"source": "JmyJ5", "target": "plrgQ", "value": 0}, {"source": "JmyJ5", "target": "Z05e", "value": 1}, {"source": "JmyJ5", "target": "dB4dN", "value": 0}, {"source": "JmyJ5", "target": "DmWzd", "value": 0}, {"source": "JmyJ5", "target": "3jzya", "value": 0}, {"source": "JmyJ5", "target": "X9P2p", "value": 1}, {"source": "JmyJ5", "target": "RD0W", "value": 0}, {"source": "JmyJ5", "target": "7VENo", "value": 2}, {"source": "JmyJ5", "target": "wzrl", "value": 0}, {"source": "JmyJ5", "target": "rKdr7", "value": 1}, {"source": "JmyJ5", "target": "BA2bD", "value": 1}, {"source": "JmyJ5", "target": "O4Pw2", "value": 0}, {"source": "JmyJ5", "target": "AVDr", "value": 0}, {"source": "JmyJ5", "target": "6Rnw", "value": 0}, {"source": "JmyJ5", "target": "gpDzZ", "value": 0}, {"source": "JmyJ5", "target": "vZlPb", "value": 0}, {"source": "JmyJ5", "target": "va8O", "value": 0}, {"source": "JmyJ5", "target": "X9rGX", "value": 2}, {"source": "JmyJ5", "target": "ypvqZ", "value": 0}, {"source": "JmyJ5", "target": "q0gXm", "value": 0}, {"source": "JmyJ5", "target": "Dmnwa", "value": 0}, {"source": "JmyJ5", "target": "z2vKy", "value": 0}, {"source": "JmyJ5", "target": "rKK3N", "value": 0}, {"source": "rKv0m", "target": "Ewo0o", "value": 0}, {"source": "RADPG", "target": "pAvn", "value": 0}, {"source": "RADPG", "target": "Algmq", "value": 0}, {"source": "RADPG", "target": "JmyJ5", "value": 0}, {"source": "RADPG", "target": "K3NRz", "value": 0}, {"source": "RADPG", "target": "NAzXk", "value": 0}, {"source": "RADPG", "target": "gZa1d", "value": 0}, {"source": "aaXA", "target": "Z05e", "value": 0}, {"source": "aaXA", "target": "vZlPb", "value": 0}, {"source": "aaXA", "target": "jNZal", "value": 0}, {"source": "aaXA", "target": "27bv", "value": 0}, {"source": "O4Peb", "target": "grz5", "value": 0}, {"source": "NApZ0", "target": "WvB5", "value": 0}, {"source": "NApZ0", "target": "BAb5W", "value": 0}, {"source": "NApZ0", "target": "27bv", "value": 0}, {"source": "NApZ0", "target": "Z05e", "value": 0}, {"source": "NApZ0", "target": "JmyJ5", "value": 0}, {"source": "NApZ0", "target": "K3NRz", "value": 0}, {"source": "NApZ0", "target": "84P2", "value": 0}, {"source": "54aA5", "target": "vZlPb", "value": 0}, {"source": "54aA5", "target": "7VENo", "value": 0}, {"source": "jZ80X", "target": "QXX3", "value": 0}, {"source": "QDVbK", "target": "BvEBp", "value": 0}, {"source": "yoyZ", "target": "K3NRz", "value": 0}, {"source": "qnJ7", "target": "O9GE1", "value": 0}, {"source": "BAb5W", "target": "pB11", "value": 0}, {"source": "BAb5W", "target": "vZ79R", "value": 1}, {"source": "BAb5W", "target": "3ppvb", "value": 1}, {"source": "BAb5W", "target": "BvOmV", "value": 0}, {"source": "BAb5W", "target": "7VENo", "value": 3}, {"source": "BAb5W", "target": "pKXan", "value": 0}, {"source": "BAb5W", "target": "gZBWl", "value": 1}, {"source": "BAb5W", "target": "6rdD", "value": 0}, {"source": "BAb5W", "target": "wyv9v", "value": 0}, {"source": "BAb5W", "target": "JmyJ5", "value": 0}, {"source": "BAb5W", "target": "K3NRz", "value": 4}, {"source": "BAb5W", "target": "rKdr7", "value": 0}, {"source": "BAb5W", "target": "m8eb", "value": 0}, {"source": "BAb5W", "target": "va8O", "value": 0}, {"source": "BAb5W", "target": "Ew8zB", "value": 1}, {"source": "BAb5W", "target": "OaR9", "value": 0}, {"source": "BAb5W", "target": "kD6Nv", "value": 0}, {"source": "BAb5W", "target": "55RNe", "value": 0}, {"source": "BAb5W", "target": "Nb3q0", "value": 0}, {"source": "wzrl", "target": "Alr5l", "value": 0}, {"source": "wzrl", "target": "grz5", "value": 0}, {"source": "wzrl", "target": "O94g1", "value": 0}, {"source": "7yBk", "target": "oy3PX", "value": 0}, {"source": "lypB1", "target": "7VENo", "value": 0}, {"source": "lypB1", "target": "grz5", "value": 0}, {"source": "lypB1", "target": "Ewo0o", "value": 1}, {"source": "RAV8Z", "target": "wzrl", "value": 0}, {"source": "q0Egm", "target": "O94g1", "value": 0}, {"source": "RW2Xr", "target": "KmbwJ", "value": 0}, {"source": "RW2Xr", "target": "gZBVW", "value": 0}, {"source": "RW2Xr", "target": "QpzWK", "value": 0}, {"source": "RW2Xr", "target": "kg0E", "value": 0}, {"source": "RW2Xr", "target": "GVZqw", "value": 1}, {"source": "RW2Xr", "target": "Wqol5", "value": 4}, {"source": "RW2Xr", "target": "mj3DZ", "value": 1}, {"source": "RW2Xr", "target": "XJKzK", "value": 0}, {"source": "RW2Xr", "target": "q07yR", "value": 0}, {"source": "eRNNb", "target": "oy3PX", "value": 0}, {"source": "eRNNb", "target": "Z05e", "value": 4}, {"source": "eRNNb", "target": "jNpWr", "value": 0}, {"source": "eRNNb", "target": "D9ep", "value": 0}, {"source": "eRNNb", "target": "b7P6", "value": 2}, {"source": "eRNNb", "target": "549zm", "value": 1}, {"source": "eRNNb", "target": "NAnpm", "value": 1}, {"source": "eRNNb", "target": "WvB5", "value": 2}, {"source": "eRNNb", "target": "RD0W", "value": 0}, {"source": "eRNNb", "target": "Alr5l", "value": 0}, {"source": "eRNNb", "target": "Q7XK", "value": 0}, {"source": "eRNNb", "target": "Gk2e", "value": 0}, {"source": "eRNNb", "target": "vZ79R", "value": 0}, {"source": "eRNNb", "target": "EweRP", "value": 0}, {"source": "eRNNb", "target": "BvOmV", "value": 0}, {"source": "eRNNb", "target": "BA2bD", "value": 0}, {"source": "eRNNb", "target": "vZBB9", "value": 0}, {"source": "eRNNb", "target": "qBj55", "value": 0}, {"source": "eRNNb", "target": "JmyJ5", "value": 3}, {"source": "eRNNb", "target": "vZlPb", "value": 0}, {"source": "eRNNb", "target": "pKaBX", "value": 0}, {"source": "eRNNb", "target": "27bv", "value": 2}, {"source": "eRNNb", "target": "Q2Ko", "value": 0}, {"source": "eRNNb", "target": "rKdr7", "value": 10}, {"source": "Nw6m", "target": "oyplN", "value": 0}, {"source": "q01l2", "target": "7Vj8b", "value": 0}, {"source": "pB11", "target": "BAb5W", "value": 0}, {"source": "pB11", "target": "pKXan", "value": 0}, {"source": "pB11", "target": "vZBB9", "value": 0}, {"source": "pB11", "target": "Q7XK", "value": 0}, {"source": "pB11", "target": "Gk2e", "value": 0}, {"source": "pKXan", "target": "kBwJE", "value": 0}, {"source": "pKXan", "target": "pB11", "value": 0}, {"source": "pKXan", "target": "Q2Ko", "value": 0}, {"source": "pKXan", "target": "K3NRz", "value": 0}, {"source": "qBqo9", "target": "BvEBp", "value": 0}, {"source": "qBqo9", "target": "rKdr7", "value": 0}, {"source": "qBqo9", "target": "pAvn", "value": 0}, {"source": "8zVOA", "target": "K3NRz", "value": 0}, {"source": "GV7pK", "target": "qnJ7", "value": 0}, {"source": "NA2Na", "target": "w8kA", "value": 0}, {"source": "NA2Na", "target": "J3j4y", "value": 0}, {"source": "NA2Na", "target": "AVDr", "value": 1}, {"source": "NA2Na", "target": "Qpmen", "value": 0}, {"source": "NA2Na", "target": "K3NRz", "value": 2}, {"source": "NA2Na", "target": "Ew8zB", "value": 0}, {"source": "Nb3q0", "target": "WvB5", "value": 0}, {"source": "Nb3q0", "target": "06Zod", "value": 1}, {"source": "Nb3q0", "target": "z9OGK", "value": 3}, {"source": "Nb3q0", "target": "4Wnbq", "value": 0}, {"source": "Nb3q0", "target": "gZBWl", "value": 0}, {"source": "Nb3q0", "target": "a7ld3", "value": 1}, {"source": "Nb3q0", "target": "Z05e", "value": 0}, {"source": "Nb3q0", "target": "K3NRz", "value": 0}, {"source": "Nb3q0", "target": "Q2Ko", "value": 0}, {"source": "Nb3q0", "target": "jNZal", "value": 2}, {"source": "Nb3q0", "target": "NAzXk", "value": 0}, {"source": "Nb3q0", "target": "Gk2e", "value": 2}, {"source": "Nb3q0", "target": "va8O", "value": 3}, {"source": "Nb3q0", "target": "jNq8m", "value": 1}, {"source": "Nb3q0", "target": "Dmnwa", "value": 2}, {"source": "Nb3q0", "target": "7VENo", "value": 1}, {"source": "Nb3q0", "target": "qBj55", "value": 1}, {"source": "Nb3q0", "target": "54aBr", "value": 0}, {"source": "Nb3q0", "target": "pAvn", "value": 0}, {"source": "1Oeq", "target": "1jVBk", "value": 0}, {"source": "GqKJ", "target": "Ewo0o", "value": 0}, {"source": "v2jOz", "target": "BAb5W", "value": 0}, {"source": "v2jOz", "target": "grz5", "value": 1}, {"source": "v2jOz", "target": "BvEBp", "value": 1}, {"source": "o4Qee", "target": "b7P6", "value": 0}, {"source": "Algmq", "target": "r1Xr", "value": 0}, {"source": "XJKzK", "target": "K3NRz", "value": 0}, {"source": "XJKzK", "target": "ND5J", "value": 2}, {"source": "XJKzK", "target": "3jJDk", "value": 0}, {"source": "Dm20P", "target": "K3NRz", "value": 1}, {"source": "Dm20P", "target": "7VENo", "value": 0}, {"source": "Dm20P", "target": "1jVBk", "value": 0}, {"source": "wy5AK", "target": "EweRP", "value": 0}, {"source": "wy5AK", "target": "BvOmV", "value": 0}, {"source": "wy5AK", "target": "7VENo", "value": 0}, {"source": "K602", "target": "lyZ61", "value": 0}, {"source": "1r0Z", "target": "0jrn3", "value": 0}, {"source": "7p5NB", "target": "7VENo", "value": 0}, {"source": "QXX3", "target": "gZmOd", "value": 0}, {"source": "pXEy", "target": "1jVBk", "value": 0}, {"source": "pXEy", "target": "pAvn", "value": 0}, {"source": "8rBVm", "target": "jN9Nr", "value": 0}, {"source": "8rBVm", "target": "K3NRz", "value": 1}, {"source": "8rBVm", "target": "BAb5W", "value": 1}, {"source": "8rBVm", "target": "vZlPb", "value": 1}, {"source": "O98ez", "target": "vZlPb", "value": 1}, {"source": "m8eb", "target": "BAb5W", "value": 0}, {"source": "m8eb", "target": "BvEBp", "value": 1}, {"source": "m8eb", "target": "Ewo0o", "value": 0}, {"source": "m8eb", "target": "790o", "value": 0}, {"source": "m8eb", "target": "pAvn", "value": 0}, {"source": "m8eb", "target": "zJrw", "value": 0}, {"source": "m8eb", "target": "oy3PX", "value": 1}, {"source": "m8eb", "target": "lyZ61", "value": 0}, {"source": "m8eb", "target": "gZmOd", "value": 0}, {"source": "m8eb", "target": "wyv9v", "value": 0}, {"source": "m8eb", "target": "K3NRz", "value": 1}, {"source": "m8eb", "target": "vZlPb", "value": 2}, {"source": "m8eb", "target": "27bv", "value": 0}, {"source": "m8eb", "target": "BvOmV", "value": 0}, {"source": "m8eb", "target": "84P2", "value": 0}, {"source": "m8eb", "target": "J3j4y", "value": 0}, {"source": "m8eb", "target": "gZa1d", "value": 0}, {"source": "m8eb", "target": "wzrl", "value": 0}, {"source": "06W9Z", "target": "grz5", "value": 0}, {"source": "3ppvb", "target": "BvOmV", "value": 1}, {"source": "3ppvb", "target": "BA2bD", "value": 0}, {"source": "3ppvb", "target": "Nb3q0", "value": 0}, {"source": "3ppvb", "target": "K3NRz", "value": 2}, {"source": "3ppvb", "target": "Qbro", "value": 0}, {"source": "3ppvb", "target": "O94g1", "value": 0}, {"source": "3ppvb", "target": "27bv", "value": 0}, {"source": "3ppvb", "target": "vZlPb", "value": 0}, {"source": "3ppvb", "target": "Dmnwa", "value": 1}, {"source": "3ppvb", "target": "O4vdj", "value": 0}, {"source": "3ppvb", "target": "Z9n1B", "value": 0}, {"source": "3ppvb", "target": "06W9Z", "value": 0}, {"source": "pRX1", "target": "oyweQ", "value": 0}, {"source": "rKdr7", "target": "WvB5", "value": 1}, {"source": "rKdr7", "target": "yoyZ", "value": 0}, {"source": "rKdr7", "target": "wzrl", "value": 0}, {"source": "rKdr7", "target": "qBqo9", "value": 0}, {"source": "rKdr7", "target": "eRNNb", "value": 2}, {"source": "rKdr7", "target": "plrgQ", "value": 0}, {"source": "rKdr7", "target": "gZmOd", "value": 3}, {"source": "rKdr7", "target": "JmyJ5", "value": 1}, {"source": "rKdr7", "target": "Alr5l", "value": 0}, {"source": "rKdr7", "target": "vZlPb", "value": 0}, {"source": "rKdr7", "target": "GXAn", "value": 0}, {"source": "rKdr7", "target": "jNq8m", "value": 2}, {"source": "rKdr7", "target": "gZa1d", "value": 0}, {"source": "ebZ9", "target": "J3j4y", "value": 0}, {"source": "ebZ9", "target": "vWD9", "value": 0}, {"source": "ebZ9", "target": "27bv", "value": 0}, {"source": "ebZ9", "target": "va8O", "value": 1}, {"source": "ebZ9", "target": "Gk2e", "value": 0}, {"source": "XJGOp", "target": "pKaBX", "value": 0}, {"source": "RzA1", "target": "84P2", "value": 0}, {"source": "Gbpd", "target": "BAb5W", "value": 0}, {"source": "Gbpd", "target": "K3NRz", "value": 2}, {"source": "Gbpd", "target": "vZlPb", "value": 0}, {"source": "Gbpd", "target": "jNZal", "value": 0}, {"source": "Gbpd", "target": "vZ79R", "value": 0}, {"source": "Gbpd", "target": "kD6Nv", "value": 1}, {"source": "Gbpd", "target": "OaR9", "value": 0}, {"source": "KrrD", "target": "27bv", "value": 0}, {"source": "KrrD", "target": "rKdr7", "value": 0}, {"source": "JVQy", "target": "grz5", "value": 0}, {"source": "8rGk2", "target": "BAb5W", "value": 0}, {"source": "8rGk2", "target": "BA2bD", "value": 0}, {"source": "8rGk2", "target": "O4Pw2", "value": 0}, {"source": "8rGk2", "target": "27bv", "value": 0}, {"source": "8rGk2", "target": "pKaBX", "value": 0}, {"source": "8rGk2", "target": "m8eb", "value": 0}, {"source": "8rGk2", "target": "K3NRz", "value": 1}, {"source": "8rGk2", "target": "jNZal", "value": 0}, {"source": "8rGk2", "target": "7VENo", "value": 0}, {"source": "8rGk2", "target": "kD6Nv", "value": 1}, {"source": "qBrBv", "target": "Ewo0o", "value": 0}, {"source": "lNd3m", "target": "Q2Ko", "value": 0}, {"source": "BA935", "target": "BAb5W", "value": 0}, {"source": "BA935", "target": "X9P2p", "value": 0}, {"source": "BA935", "target": "790o", "value": 0}, {"source": "BA935", "target": "O94g1", "value": 0}, {"source": "BA935", "target": "JmyJ5", "value": 0}, {"source": "BA935", "target": "kBwJE", "value": 0}, {"source": "BA935", "target": "WEQVX", "value": 0}, {"source": "BA935", "target": "rKdr7", "value": 0}, {"source": "BA935", "target": "m8eb", "value": 0}, {"source": "BA935", "target": "v2jOz", "value": 0}, {"source": "erGw", "target": "WvB5", "value": 0}, {"source": "erGw", "target": "ypAyZ", "value": 0}, {"source": "erGw", "target": "EweRP", "value": 0}, {"source": "erGw", "target": "m8eb", "value": 0}, {"source": "erGw", "target": "K3NRz", "value": 1}, {"source": "erGw", "target": "vZlPb", "value": 0}, {"source": "erGw", "target": "vZ2bO", "value": 0}, {"source": "erGw", "target": "0jrn3", "value": 0}, {"source": "JZbA", "target": "vZlPb", "value": 0}, {"source": "X9aDe", "target": "Q2Ko", "value": 0}, {"source": "X9aDe", "target": "DmWzd", "value": 0}, {"source": "X9aDe", "target": "vZlPb", "value": 0}, {"source": "X9aDe", "target": "jNlNl", "value": 0}, {"source": "jNNb4", "target": "06Zod", "value": 0}, {"source": "jNNb4", "target": "kD6Nv", "value": 0}, {"source": "jNNb4", "target": "rKK3N", "value": 0}, {"source": "b9NZw", "target": "vZBB9", "value": 0}, {"source": "b9NZw", "target": "K3NRz", "value": 0}, {"source": "b9NZw", "target": "gZBWl", "value": 0}, {"source": "z2OGw", "target": "ZANE", "value": 0}, {"source": "Nn8k", "target": "JegB", "value": 0}, {"source": "Nn8k", "target": "dBvVK", "value": 0}, {"source": "Nn8k", "target": "jNZal", "value": 0}, {"source": "Nn8k", "target": "jNq8m", "value": 0}, {"source": "Nn8k", "target": "kD6Nv", "value": 0}, {"source": "Nn8k", "target": "OaR9", "value": 1}, {"source": "qBOv7", "target": "Qpmen", "value": 0}, {"source": "4W2W9", "target": "yypd9", "value": 0}, {"source": "Z9n1B", "target": "O94g1", "value": 1}, {"source": "Z9n1B", "target": "BvEBp", "value": 0}, {"source": "Z9n1B", "target": "n9l7", "value": 0}, {"source": "Z9n1B", "target": "wzrl", "value": 0}, {"source": "PB0p9", "target": "Ew8zB", "value": 0}, {"source": "GV7ow", "target": "oy3PX", "value": 0}, {"source": "kD6Nv", "target": "Ewo0o", "value": 0}, {"source": "kD6Nv", "target": "J6k5", "value": 0}, {"source": "kD6Nv", "target": "DmWzd", "value": 0}, {"source": "kD6Nv", "target": "jNNb4", "value": 0}, {"source": "kD6Nv", "target": "D9ep", "value": 1}, {"source": "kD6Nv", "target": "NAnpm", "value": 0}, {"source": "kD6Nv", "target": "WvB5", "value": 2}, {"source": "kD6Nv", "target": "BAb5W", "value": 1}, {"source": "kD6Nv", "target": "7VENo", "value": 2}, {"source": "kD6Nv", "target": "pAvn", "value": 0}, {"source": "kD6Nv", "target": "4W3JZ", "value": 1}, {"source": "kD6Nv", "target": "oyweQ", "value": 0}, {"source": "kD6Nv", "target": "84P2", "value": 0}, {"source": "kD6Nv", "target": "OaR9", "value": 3}, {"source": "kD6Nv", "target": "GPpOo", "value": 4}, {"source": "kD6Nv", "target": "O45Ey", "value": 2}, {"source": "kD6Nv", "target": "AVDr", "value": 0}, {"source": "kD6Nv", "target": "vZBB9", "value": 1}, {"source": "kD6Nv", "target": "a7ld3", "value": 0}, {"source": "kD6Nv", "target": "El8g", "value": 0}, {"source": "kD6Nv", "target": "Jjkp", "value": 1}, {"source": "kD6Nv", "target": "jNZal", "value": 1}, {"source": "kD6Nv", "target": "NAzXk", "value": 0}, {"source": "kD6Nv", "target": "va8O", "value": 0}, {"source": "kD6Nv", "target": "Gbpd", "value": 1}, {"source": "kD6Nv", "target": "06Zod", "value": 2}, {"source": "kD6Nv", "target": "K3NRz", "value": 3}, {"source": "kD6Nv", "target": "ypdWw", "value": 0}, {"source": "kD6Nv", "target": "q0gXm", "value": 2}, {"source": "kD6Nv", "target": "jNq8m", "value": 0}, {"source": "kD6Nv", "target": "6rdD", "value": 0}, {"source": "kD6Nv", "target": "q07yR", "value": 0}, {"source": "mj3X3", "target": "1KOE", "value": 0}, {"source": "Qbro", "target": "ZANE", "value": 0}, {"source": "Qbro", "target": "K3NRz", "value": 0}, {"source": "wyRlO", "target": "O9GE1", "value": 0}, {"source": "wyRlO", "target": "ZANE", "value": 0}, {"source": "GVOZn", "target": "gZmOd", "value": 0}, {"source": "o4J4z", "target": "vZlPb", "value": 0}, {"source": "6rdD", "target": "Jjkp", "value": 0}]}